Workbook

Sheet How to use
A1: HIUSA QA test sheet
A3: What this is for
A4: 1. Each tab (SAO, Department Head, Admin & Adviser, SBO Officer, Student, General) lists test cases for one role.
A5: 2. Sign in with the account for that role, follow the Steps column, and compare what happens with the Expected result.
A6: 3. Set the Status for every case you run. Fill Tester, Date tested, and the device and browser you used.
A7: 4. If a case fails, set Severity, describe what you saw in Actual result / notes, and paste a screenshot link.
A8: 5. The Summary tab counts your entries by itself. Do not type in it.
A10: Test link
A11: Ask the host for the current link; it changes if the host restarts it.
A13: Test accounts
A14: Role | B14: School ID | C14: Notes
A15: SAO | B15: 990001 | C15: The only SAO account on the test copy. Runs the university side.
A16: Department Head | B16: 940001 to 940009 | C16: 940001 College of Computer Studies, 940002 Business Education, 940003 Teacher Education, 940004 Health Sciences, 940005 Engineering, 940006 Criminal Justice Education, 940007 Hospitality, Tourism and Customs Administration, 940008 Maritime Education, 940009 Nursing. One head per college; pick the college you were assigned.
A17: Admin (Organization Admin) | B17: 900001 to 900003, 920011 | C17: 900001 President, 900002 Vice President Internal, 900003 Secretary (all PSITS-CCS). 920011 is the President of JPIA-CBE.
A18: Adviser | B18: 990002, 990012, 990022, 990032, 990042 | C18: An Admin assigned by the SAO. 990002 PSITS-CCS, 990012 JPIA-CBE, 990022 FES-CTE, 990032 NSC-CHS, 990042 EIG-COE. Same menu as an Admin.
A19: SBO Officer | B19: 900004 to 900007 | C19: 900004 Treasurer, 900005 Auditor, 900006 Public Information Officer, 900007 Business Manager (all PSITS-CCS).
A20: Student | B20: 2100142 | C20: PSITS-CCS. Also 2100217, 2100389, 2200055, 2200134, 2200298, 2200451, 2300078, 2300163, 2300247, 2300312, 2400019, 2400067, 2400093. 2400118 belongs to FES-CTE and 2400133 to EIG-COE.
A21: Passwords: ask the host. Never share one account between two testers, because 5 wrong passwords lock it for 15 minutes.
A23: Status legend
A24: Not run | B24: Not tried yet. This is the starting value.
A25: Pass | B25: You ran every step and the result matched the Expected result.
A26: Fail | B26: You ran the steps and the result did not match. Set a Severity and describe it.
A27: Blocked | B27: You could not run it because something earlier is broken or missing (say what in the notes).
A28: N/A | B28: The case does not apply to you, for example a phone-only case on a laptop.
A30: How to report a bug
A31: Write these in the row of the failed case (Actual result / notes), or send them to the host:
A32: 1. Role and page (for example "Student, Store, Shop").
A33: 2. What you did, step by step.
A34: 3. What you expected.
A35: 4. What actually happened, with the exact message if there was one.
A36: 5. A screenshot, linked in the Bug screenshot link column.
A37: 6. Whether you used a phone or a laptop, and which browser.
A38: Severity: Critical = cannot continue or data is wrong or lost; Major = a feature does not work; Minor = works but is awkward or has a workaround; Cosmetic = looks wrong only.
A40: Run order
A41: Before anyone tests the Department Head registration cases, the SAO must set up a semester: sign in as the SAO (990001), open Academic years under Setup and records, add a semester that covers the whole test period, then choose Set as active on it. Adding it is not enough; it starts as upcoming. See docs/MEMBER_TESTING.md sections 3 and 4.
A42: Opening a semester hides the seeded events, tasks and election (they belong to no semester). So run the cases that use them first, then activate the semester and run the rest.
... A48: Blocked means you could not run the case because something it depends on failed or does not exist (write what in the notes). Cases that wait for a scheduled job run by the host and show nothing after waiting 3 minutes should be marked Blocked, with a note saying so.

Sheet Summary
A1: Summary (fills in by itself from the role tabs)
A3: Role | B3: Total | C3: Not run | D3: Pass | E3: Fail | F3: Blocked | G3: N/A | H3: Pass rate | I3: Progress | J3: Critical bugs | K3: Major bugs | L3: Minor bugs | M3: Cosmetic bugs
A4: SAO | B4: =COUNTA('SAO'!$A$2:$A$2000) -> 114 | C4: =B4-D4-E4-F4-G4 -> 114 | D4: =COUNTIF('SAO'!$M$2:$M$2000,"Pass") -> 0 | E4: =COUNTIF('SAO'!$M$2:$M$2000,"Fail") -> 0 | F4: =COUNTIF('SAO'!$M$2:$M$2000,"Blocked") -> 0 | G4: =COUNTIF('SAO'!$M$2:$M$2000,"N/A") -> 0 | H4: =IF(D4+E4=0,"",D4/(D4+E4)) | I4: =IF(B4=0,"",(B4-C4)/B4) -> 0 | J4: =COUNTIFS('SAO'!$M$2:$M$2000,"Fail",'SAO'!$N$2:$N$2000,"Critical") -> 0 | K4: =COUNTIFS('SAO'!$M$2:$M$2000,"Fail",'SAO'!$N$2:$N$2000,"Major") -> 0 | L4: =COUNTIFS('SAO'!$M$2:$M$2000,"Fail",'SAO'!$N$2:$N$2000,"Minor") -> 0 | M4: =COUNTIFS('SAO'!$M$2:$M$2000,"Fail",'SAO'!$N$2:$N$2000,"Cosmetic") -> 0
A5: Department Head | B5: =COUNTA('Department Head'!$A$2:$A$2000) -> 92 | C5: =B5-D5-E5-F5-G5 -> 92 | D5: =COUNTIF('Department Head'!$M$2:$M$2000,"Pass") -> 0 | E5: =COUNTIF('Department Head'!$M$2:$M$2000,"Fail") -> 0 | F5: =COUNTIF('Department Head'!$M$2:$M$2000,"Blocked") -> 0 | G5: =COUNTIF('Department Head'!$M$2:$M$2000,"N/A") -> 0 | H5: =IF(D5+E5=0,"",D5/(D5+E5)) | I5: =IF(B5=0,"",(B5-C5)/B5) -> 0 | J5: =COUNTIFS('Department Head'!$M$2:$M$2000,"Fail",'Department Head'!$N$2:$N$2000,"Critical") -> 0 | K5: =COUNTIFS('Department Head'!$M$2:$M$2000,"Fail",'Department Head'!$N$2:$N$2000,"Major") -> 0 | L5: =COUNTIFS('Department Head'!$M$2:$M$2000,"Fail",'Department Head'!$N$2:$N$2000,"Minor") -> 0 | M5: =COUNTIFS('Department Head'!$M$2:$M$2000,"Fail",'Department Head'!$N$2:$N$2000,"Cosmetic") -> 0
A6: Admin & Adviser | B6: =COUNTA('Admin & Adviser'!$A$2:$A$2000) -> 243 | C6: =B6-D6-E6-F6-G6 -> 243 | D6: =COUNTIF('Admin & Adviser'!$M$2:$M$2000,"Pass") -> 0 | E6: =COUNTIF('Admin & Adviser'!$M$2:$M$2000,"Fail") -> 0 | F6: =COUNTIF('Admin & Adviser'!$M$2:$M$2000,"Blocked") -> 0 | G6: =COUNTIF('Admin & Adviser'!$M$2:$M$2000,"N/A") -> 0 | H6: =IF(D6+E6=0,"",D6/(D6+E6)) | I6: =IF(B6=0,"",(B6-C6)/B6) -> 0 | J6: =COUNTIFS('Admin & Adviser'!$M$2:$M$2000,"Fail",'Admin & Adviser'!$N$2:$N$2000,"Critical") -> 0 | K6: =COUNTIFS('Admin & Adviser'!$M$2:$M$2000,"Fail",'Admin & Adviser'!$N$2:$N$2000,"Major") -> 0 | L6: =COUNTIFS('Admin & Adviser'!$M$2:$M$2000,"Fail",'Admin & Adviser'!$N$2:$N$2000,"Minor") -> 0 | M6: =COUNTIFS('Admin & Adviser'!$M$2:$M$2000,"Fail",'Admin & Adviser'!$N$2:$N$2000,"Cosmetic") -> 0
A7: SBO Officer | B7: =COUNTA('SBO Officer'!$A$2:$A$2000) -> 94 | C7: =B7-D7-E7-F7-G7 -> 94 | D7: =COUNTIF('SBO Officer'!$M$2:$M$2000,"Pass") -> 0 | E7: =COUNTIF('SBO Officer'!$M$2:$M$2000,"Fail") -> 0 | F7: =COUNTIF('SBO Officer'!$M$2:$M$2000,"Blocked") -> 0 | G7: =COUNTIF('SBO Officer'!$M$2:$M$2000,"N/A") -> 0 | H7: =IF(D7+E7=0,"",D7/(D7+E7)) | I7: =IF(B7=0,"",(B7-C7)/B7) -> 0 | J7: =COUNTIFS('SBO Officer'!$M$2:$M$2000,"Fail",'SBO Officer'!$N$2:$N$2000,"Critical") -> 0 | K7: =COUNTIFS('SBO Officer'!$M$2:$M$2000,"Fail",'SBO Officer'!$N$2:$N$2000,"Major") -> 0 | L7: =COUNTIFS('SBO Officer'!$M$2:$M$2000,"Fail",'SBO Officer'!$N$2:$N$2000,"Minor") -> 0 | M7: =COUNTIFS('SBO Officer'!$M$2:$M$2000,"Fail",'SBO Officer'!$N$2:$N$2000,"Cosmetic") -> 0
A8: Student | B8: =COUNTA('Student'!$A$2:$A$2000) -> 108 | C8: =B8-D8-E8-F8-G8 -> 108 | D8: =COUNTIF('Student'!$M$2:$M$2000,"Pass") -> 0 | E8: =COUNTIF('Student'!$M$2:$M$2000,"Fail") -> 0 | F8: =COUNTIF('Student'!$M$2:$M$2000,"Blocked") -> 0 | G8: =COUNTIF('Student'!$M$2:$M$2000,"N/A") -> 0 | H8: =IF(D8+E8=0,"",D8/(D8+E8)) | I8: =IF(B8=0,"",(B8-C8)/B8) -> 0 | J8: =COUNTIFS('Student'!$M$2:$M$2000,"Fail",'Student'!$N$2:$N$2000,"Critical") -> 0 | K8: =COUNTIFS('Student'!$M$2:$M$2000,"Fail",'Student'!$N$2:$N$2000,"Major") -> 0 | L8: =COUNTIFS('Student'!$M$2:$M$2000,"Fail",'Student'!$N$2:$N$2000,"Minor") -> 0 | M8: =COUNTIFS('Student'!$M$2:$M$2000,"Fail",'Student'!$N$2:$N$2000,"Cosmetic") -> 0
A9: General | B9: =COUNTA('General'!$A$2:$A$2000) -> 129 | C9: =B9-D9-E9-F9-G9 -> 129 | D9: =COUNTIF('General'!$M$2:$M$2000,"Pass") -> 0 | E9: =COUNTIF('General'!$M$2:$M$2000,"Fail") -> 0 | F9: =COUNTIF('General'!$M$2:$M$2000,"Blocked") -> 0 | G9: =COUNTIF('General'!$M$2:$M$2000,"N/A") -> 0 | H9: =IF(D9+E9=0,"",D9/(D9+E9)) | I9: =IF(B9=0,"",(B9-C9)/B9) -> 0 | J9: =COUNTIFS('General'!$M$2:$M$2000,"Fail",'General'!$N$2:$N$2000,"Critical") -> 0 | K9: =COUNTIFS('General'!$M$2:$M$2000,"Fail",'General'!$N$2:$N$2000,"Major") -> 0 | L9: =COUNTIFS('General'!$M$2:$M$2000,"Fail",'General'!$N$2:$N$2000,"Minor") -> 0 | M9: =COUNTIFS('General'!$M$2:$M$2000,"Fail",'General'!$N$2:$N$2000,"Cosmetic") -> 0
A10: All roles | B10: =SUM(B4:B9) -> 780 | C10: =SUM(C4:C9) -> 780 | D10: =SUM(D4:D9) -> 0 | E10: =SUM(E4:E9) -> 0 | F10: =SUM(F4:F9) -> 0 | G10: =SUM(G4:G9) -> 0 | H10: =IF(D10+E10=0,"",D10/(D10+E10)) | I10: =IF(B10=0,"",(B10-C10)/B10) -> 0 | J10: =SUM(J4:J9) -> 0 | K10: =SUM(K4:K9) -> 0 | L10: =SUM(L4:L9) -> 0 | M10: =SUM(M4:M9) -> 0
A12: Total = number of test cases on the tab. Not run = Total minus Pass, Fail, Blocked and N/A.
A13: Pass rate = Pass / (Pass + Fail). It only counts cases that were actually run to a result; Not run, Blocked and N/A are left out.
A14: Progress = (Total - Not run) / Total. It counts every case that has any status other than Not run.
A15: Bug columns count cases with Status = Fail and the matching Severity. A Fail with no Severity is in Fail but in none of the bug columns.
A16: Formulas read rows 2 to 2000 of each tab, so cases added below the last row are counted.
A18: By round
A19: Round | B19: Total | C19: Pass | D19: Fail | E19: Blocked
A20: Round 1 (before the SAO opens a semester) | B20: =COUNTIFS('SAO'!$G$2:$G$2000,$A20)+COUNTIFS('Department Head'!$G$2:$G$2000,$A20)+COUNTIFS('Admin & Adviser'!$G$2:$G$2000,$A20)+COUNTIFS('SBO Officer'!$G$2:$G$2000,$A20)+COUNTIFS('Student'!$G$2:$G$2000,$A20)+COUNTIFS('General'!$G$2:$G$2000,$A20) -> 24 | C20: =COUNTIFS('SAO'!$G$2:$G$2000,$A20,'SAO'!$M$2:$M$2000,"Pass")+COUNTIFS('Department Head'!$G$2:$G$2000,$A20,'Department Head'!$M$2:$M$2000,"Pass")+COUNTIFS('Admin & Adviser'!$G$2:$G$2000,$A20,'Admin & Adviser'!$M$2:$M$2000,"Pass")+COUNTIFS('SBO Officer'!$G$2:$G$2000,$A20,'SBO Officer'!$M$2:$M$2000,"Pass")+COUNTIFS('Student'!$G$2:$G$2000,$A20,'Student'!$M$2:$M$2000,"Pass")+COUNTIFS('General'!$G$2:$G$2000,$A20,'General'!$M$2:$M$2000,"Pass") -> 0 | D20: =COUNTIFS('SAO'!$G$2:$G$2000,$A20,'SAO'!$M$2:$M$2000,"Fail")+COUNTIFS('Department Head'!$G$2:$G$2000,$A20,'Department Head'!$M$2:$M$2000,"Fail")+COUNTIFS('Admin & Adviser'!$G$2:$G$2000,$A20,'Admin & Adviser'!$M$2:$M$2000,"Fail")+COUNTIFS('SBO Officer'!$G$2:$G$2000,$A20,'SBO Officer'!$M$2:$M$2000,"Fail")+COUNTIFS('Student'!$G$2:$G$2000,$A20,'Student'!$M$2:$M$2000,"Fail")+COUNTIFS('General'!$G$2:$G$2000,$A20,'General'!$M$2:$M$2000,"Fail") -> 0 | E20: =COUNTIFS('SAO'!$G$2:$G$2000,$A20,'SAO'!$M$2:$M$2000,"Blocked")+COUNTIFS('Department Head'!$G$2:$G$2000,$A20,'Department Head'!$M$2:$M$2000,"Blocked")+COUNTIFS('Admin & Adviser'!$G$2:$G$2000,$A20,'Admin & Adviser'!$M$2:$M$2000,"Blocked")+COUNTIFS('SBO Officer'!$G$2:$G$2000,$A20,'SBO Officer'!$M$2:$M$2000,"Blocked")+COUNTIFS('Student'!$G$2:$G$2000,$A20,'Student'!$M$2:$M$2000,"Blocked")+COUNTIFS('General'!$G$2:$G$2000,$A20,'General'!$M$2:$M$2000,"Blocked") -> 0
A21: Round 2 (after the SAO activates a semester) | B21: =COUNTIFS('SAO'!$G$2:$G$2000,$A21)+COUNTIFS('Department Head'!$G$2:$G$2000,$A21)+COUNTIFS('Admin & Adviser'!$G$2:$G$2000,$A21)+COUNTIFS('SBO Officer'!$G$2:$G$2000,$A21)+COUNTIFS('Student'!$G$2:$G$2000,$A21)+COUNTIFS('General'!$G$2:$G$2000,$A21) -> 25 | C21: =COUNTIFS('SAO'!$G$2:$G$2000,$A21,'SAO'!$M$2:$M$2000,"Pass")+COUNTIFS('Department Head'!$G$2:$G$2000,$A21,'Department Head'!$M$2:$M$2000,"Pass")+COUNTIFS('Admin & Adviser'!$G$2:$G$2000,$A21,'Admin & Adviser'!$M$2:$M$2000,"Pass")+COUNTIFS('SBO Officer'!$G$2:$G$2000,$A21,'SBO Officer'!$M$2:$M$2000,"Pass")+COUNTIFS('Student'!$G$2:$G$2000,$A21,'Student'!$M$2:$M$2000,"Pass")+COUNTIFS('General'!$G$2:$G$2000,$A21,'General'!$M$2:$M$2000,"Pass") -> 0 | D21: =COUNTIFS('SAO'!$G$2:$G$2000,$A21,'SAO'!$M$2:$M$2000,"Fail")+COUNTIFS('Department Head'!$G$2:$G$2000,$A21,'Department Head'!$M$2:$M$2000,"Fail")+COUNTIFS('Admin & Adviser'!$G$2:$G$2000,$A21,'Admin & Adviser'!$M$2:$M$2000,"Fail")+COUNTIFS('SBO Officer'!$G$2:$G$2000,$A21,'SBO Officer'!$M$2:$M$2000,"Fail")+COUNTIFS('Student'!$G$2:$G$2000,$A21,'Student'!$M$2:$M$2000,"Fail")+COUNTIFS('General'!$G$2:$G$2000,$A21,'General'!$M$2:$M$2000,"Fail") -> 0 | E21: =COUNTIFS('SAO'!$G$2:$G$2000,$A21,'SAO'!$M$2:$M$2000,"Blocked")+COUNTIFS('Department Head'!$G$2:$G$2000,$A21,'Department Head'!$M$2:$M$2000,"Blocked")+COUNTIFS('Admin & Adviser'!$G$2:$G$2000,$A21,'Admin & Adviser'!$M$2:$M$2000,"Blocked")+COUNTIFS('SBO Officer'!$G$2:$G$2000,$A21,'SBO Officer'!$M$2:$M$2000,"Blocked")+COUNTIFS('Student'!$G$2:$G$2000,$A21,'Student'!$M$2:$M$2000,"Blocked")+COUNTIFS('General'!$G$2:$G$2000,$A21,'General'!$M$2:$M$2000,"Blocked") -> 0
A22: Any time | B22: =COUNTIFS('SAO'!$G$2:$G$2000,$A22)+COUNTIFS('Department Head'!$G$2:$G$2000,$A22)+COUNTIFS('Admin & Adviser'!$G$2:$G$2000,$A22)+COUNTIFS('SBO Officer'!$G$2:$G$2000,$A22)+COUNTIFS('Student'!$G$2:$G$2000,$A22)+COUNTIFS('General'!$G$2:$G$2000,$A22) -> 731 | C22: =COUNTIFS('SAO'!$G$2:$G$2000,$A22,'SAO'!$M$2:$M$2000,"Pass")+COUNTIFS('Department Head'!$G$2:$G$2000,$A22,'Department Head'!$M$2:$M$2000,"Pass")+COUNTIFS('Admin & Adviser'!$G$2:$G$2000,$A22,'Admin & Adviser'!$M$2:$M$2000,"Pass")+COUNTIFS('SBO Officer'!$G$2:$G$2000,$A22,'SBO Officer'!$M$2:$M$2000,"Pass")+COUNTIFS('Student'!$G$2:$G$2000,$A22,'Student'!$M$2:$M$2000,"Pass")+COUNTIFS('General'!$G$2:$G$2000,$A22,'General'!$M$2:$M$2000,"Pass") -> 0 | D22: =COUNTIFS('SAO'!$G$2:$G$2000,$A22,'SAO'!$M$2:$M$2000,"Fail")+COUNTIFS('Department Head'!$G$2:$G$2000,$A22,'Department Head'!$M$2:$M$2000,"Fail")+COUNTIFS('Admin & Adviser'!$G$2:$G$2000,$A22,'Admin & Adviser'!$M$2:$M$2000,"Fail")+COUNTIFS('SBO Officer'!$G$2:$G$2000,$A22,'SBO Officer'!$M$2:$M$2000,"Fail")+COUNTIFS('Student'!$G$2:$G$2000,$A22,'Student'!$M$2:$M$2000,"Fail")+COUNTIFS('General'!$G$2:$G$2000,$A22,'General'!$M$2:$M$2000,"Fail") -> 0 | E22: =COUNTIFS('SAO'!$G$2:$G$2000,$A22,'SAO'!$M$2:$M$2000,"Blocked")+COUNTIFS('Department Head'!$G$2:$G$2000,$A22,'Department Head'!$M$2:$M$2000,"Blocked")+COUNTIFS('Admin & Adviser'!$G$2:$G$2000,$A22,'Admin & Adviser'!$M$2:$M$2000,"Blocked")+COUNTIFS('SBO Officer'!$G$2:$G$2000,$A22,'SBO Officer'!$M$2:$M$2000,"Blocked")+COUNTIFS('Student'!$G$2:$G$2000,$A22,'Student'!$M$2:$M$2000,"Blocked")+COUNTIFS('General'!$G$2:$G$2000,$A22,'General'!$M$2:$M$2000,"Blocked") -> 0
A23: Counts cases by the Round column on each role tab. Cases with no round set count under Any time.

Sheet SAO
A1: ID | B1: Module | C1: Test case | D1: Type | E1: Priority | F1: Device | G1: Round | H1: Depends on | I1: Preconditions | J1: Steps | K1: Expected result | L1: Author note (unconfirmed) | M1: Status | N1: Severity | O1: Tester | P1: Date tested | Q1: Device and browser used | R1: Actual result / notes | S1: Bug screenshot link
A2: SAO-001 | B2: Sign in and menu | C2: SAO signs in and reaches the SAO Dashboard | D2: Functional | E2: High | F2: Any | G2: Any time | I2: SAO account 990001 exists. The SAO password is given to you separately. You are signed out. | J2: 1. Open the HIUSA sign in page. 2. Type 990001 in School ID. 3. Type the SAO password in Password. 4. Select Sign in. 5. Look at the page that opens and at the left menu. | K2: You land on the SAO Dashboard (the address ends with /dashboard/super-admin). The left menu shows Dashboard, then the groups Organizations, Reviews, Updates and Setup and records, and Profile and Study objectives at the bottom. | L2: VERIFY: if a Change password screen appears first, set a new password and tell the demo owner, then continue. | M2: Not run
A3: SAO-002 | B3: Sign in and menu | C3: Sign in with a wrong password is refused | D3: Negative | E3: Medium | F3: Any | G3: Any time | I3: SAO account 990001 exists. You are signed out. | J3: 1. Open the HIUSA sign in page. 2. Type 990001 in School ID. 3. Type a wrong password in Password. 4. Select Sign in. 5. Read the message on the screen. | K3: You stay on the sign in page and a red message says the sign in failed. No Dashboard opens. Do this only once or twice: five wrong passwords lock the account for 15 minutes for everyone who shares it. | L3: VERIFY: the exact wording of the message. | M3: Not run
A4: SAO-003 | B4: Sign in and menu | C4: The SAO menu shows the right groups and pages and nothing from other roles | D4: Usability | E4: High | F4: Laptop | G4: Any time | I4: Signed in as SAO 990001. | J4: 1. Look at the left menu from top to bottom. 2. Select the group name Organizations and read the items under it. 3. Select the group name Reviews and read the items under it. 4. Select the group name Updates and read the items under it. 5. Select the group name Setup and records and read the items under it. 6. Look for any menu item named Approvals, Finance, Events, Voting or Store. | K4: The menu reads: Dashboard; Organizations (Agency overview, Registrations and organizations, Administrators, Colleges); Reviews (Compliance, Venues, Grievances, Clearances); Updates (University announcements, Notifications); Setup and records (Academic years, Audit trail); then Profile and Study objectives. Selecting a group opens its first page. The page you are on is highlighted. There is no Approvals, Finance, Events, Voting or Store item. | M4: Not run
A5: SAO-004 | B5: Sign in and menu | C5: On a phone the menu opens from the Open menu button | D5: Usability | E5: Medium | F5: Phone | G5: Any time | I5: Signed in as SAO 990001. Use a phone or a browser window narrower than 768 pixels. | J5: 1. Look at the top left of the screen for the Open menu button and select it. 2. Select the group Reviews. 3. Select Grievances. 4. Read the page title. 5. Open the menu again and select Dashboard. | K5: The menu slides in over the page. Choosing Grievances opens the Grievances page with its title. Choosing Dashboard returns to the Dashboard. The page does not scroll sideways. | L5: VERIFY: the menu closes by itself after you choose a page. | M5: Not run
A6: SAO-005 | B6: Sign in and menu | C6: Log out asks for confirmation and ends the session | D6: Functional | E6: Medium | F6: Any | G6: Any time | I6: Signed in as SAO 990001. | J6: 1. Select your name button at the top right (Account menu). 2. Select Logout. 3. Read the Log Out box, then select Cancel. 4. Select Account menu and Logout again. 5. Select Log Out in the box. 6. Press the browser Back button. | K6: The box titled Log Out says "You will need to sign in again to access your dashboard." Cancel keeps you signed in. Log Out takes you to the sign in page. Pressing Back does not show SAO data; you are asked to sign in. | L6: VERIFY: what Back shows. | M6: Not run
A7: SAO-006 | B7: Access control | C7: The SAO is sent home when it opens pages that belong to other roles | D7: Access | E7: High | F7: Laptop | G7: Any time | I7: Signed in as SAO 990001. | J7: 1. Click the address bar and replace the end of the address with /dashboard/admin, then press Enter. 2. Note which page opens. 3. Replace the address end with /dashboard/department-head/approvals and press Enter. 4. Replace the address end with /dashboard/finance/budget-allocation and press Enter. 5. Replace the address end with /dashboard/events/manage-events and press Enter. | K7: Every time the SAO is sent back to the SAO Dashboard. No page of another role is shown and no error page appears. | M7: Not run
A8: SAO-007 | B8: Access control | C8: Old SAO addresses forward to the Compliance tabs | D8: Functional | E8: Low | F8: Laptop | G8: Any time | I8: Signed in as SAO 990001. | J8: 1. Replace the address end with /dashboard/super-admin/approvals and press Enter. 2. Note the page and the selected tab. 3. Replace the address end with /dashboard/super-admin/financial-reports and press Enter. 4. Replace the address end with /dashboard/super-admin/event-requirements and press Enter. 5. Note the page and the selected tab. | K8: The first two addresses open Reviews > Compliance with the Financial reports tab selected (address ends with ?tab=financial). The third opens Compliance with the Event requirements tab selected (?tab=events). | M8: Not run
A9: SAO-008 | B9: Access control | C9: A visitor who is not signed in cannot open SAO pages | D9: Access | E9: High | F9: Any | G9: Any time | I9: You are signed out (log out first if needed). | J9: 1. Open the HIUSA address followed by /dashboard/super-admin. 2. Note which page opens. 3. Open the address followed by /dashboard/super-admin/admins. 4. Note which page opens. | K9: Both addresses show the sign in page. No SAO data is visible. | M9: Not run
A10: SAO-009 | B10: Access control | C10: Admin, Department Head and Student cannot open SAO pages | D10: Access | E10: High | F10: Laptop | G10: Any time | I10: Accounts: Admin 900001, Department Head 940001, Student 2100142. Passwords are given separately. | J10: 1. Sign in as Admin 900001. 2. Replace the address end with /dashboard/super-admin/admins and press Enter, then note the page. 3. Log out. Sign in as Department Head 940001. 4. Replace the address end with /dashboard/super-admin/organizations and press Enter, then note the page. 5. Log out. Sign in as Student 2100142. 6. Replace the address end with /dashboard/super-admin/audit-logs and press Enter, then note the page. | K10: Each person is sent back to their own home page (Admin dashboard, Department Head dashboard, Student dashboard). None of them sees an SAO page or SAO data. | M10: Not run
A11: SAO-010 | B11: Access control | C11: The SAO has no way to create an organization or a college | D11: Negative | E11: High | F11: Laptop | G11: Any time | I11: Signed in as SAO 990001. The server also answers "405 Method Not Allowed" to any request that tries to create one; automated tests pin that. | J11: 1. Open Organizations > Registrations and organizations and look at all four tabs for a New, Create, Add or Register button. 2. Open Organizations > Agency overview and look for the same buttons. 3. Open Organizations > Colleges and look for a New, Add, Create, Edit or Delete college button. 4. Count the college cards. 5. Read the buttons on one college card. | K11: There is no button to create an organization or a college anywhere. Organizations only offer Review, Open, Provision administrator, Restore and the actions menu (Edit organization, Add existing user, Manage user profiles, Archive organization). A college card only offers Manage, Assign Department Head, View organizations and Upload logo. A fresh seed shows 5 college cards. Department Heads register organizations. | M11: Not run
A12: SAO-011 | B12: Dashboard | C12: The Dashboard Review inbox lists what waits for the SAO | D12: Functional | E12: High | F12: Any | G12: Any time | I12: Signed in as SAO 990001. At least one registration or compliance submission is waiting (a Department Head 940001 has registered an organization, see Academic years first: A semester must be active first (Setup and records > Academic years, Set as active).). | J12: 1. Open Dashboard from the menu. 2. Find the card titled Review inbox. 3. Read each line and its number. 4. Select the line Registrations awaiting review. 5. Read the page that opens. | K12: Review inbox lists the queues that have work, for example Registrations awaiting review, Compliance submissions awaiting review, Financial reports to approve, Event files to approve and Venue bookings awaiting review, each with a count and a link. Registrations awaiting review opens Organizations > Registrations and organizations on the Pending review tab. | L12: VERIFY: whether a queue with zero items is hidden or shown as 0. | M12: Not run
A13: SAO-012 | B13: Dashboard | C13: The University operations numbers and the Organization filter agree with the real data | D13: Functional | E13: Medium | F13: Any | G13: Any time | I13: Signed in as SAO 990001. | J13: 1. Open Dashboard and find the card University operations. 2. Read the five numbers: Registered organizations, Active organizations, Inactive organizations, Financial reports to review, Unread Notifications. 3. Open Organizations > Agency overview and compare the Organizations and Pending reviews tiles. 4. Return to Dashboard and open the Organization filter at the top right. 5. Choose one organization from the list. 6. Read the numbers again, then choose All organizations. | K13: The numbers match the Agency overview. Filter options read "All organizations" and then "ACRONYM: Name" for each organization. After choosing one organization the numbers describe only that organization (Registered organizations shows 1). Choosing All organizations restores the totals. | M13: Not run
A14: SAO-013 | B14: Dashboard | C14: The SAO actions panel and Recent notifications lead to the right pages | D14: Functional | E14: Medium | F14: Any | G14: Any time | I14: Signed in as SAO 990001. | J14: 1. On the Dashboard find the panel SAO actions. 2. Select Registrations and organizations, read the page, then go back. 3. Do the same for Administrators, Colleges and Department Heads, Compliance and financial reports, University announcements and Notifications. 4. Scroll to Recent notifications and read it. 5. Select View all. | K14: The six links open Registrations and organizations, Administrators, Colleges, Compliance, University announcements and Notifications. Recent notifications shows titles and messages, or the sentence "No new notifications. Organization notices will appear here when they need your attention." View all opens the Notifications page. | M14: Not run
A15: SAO-014 | B15: Organizations > Agency overview | C15: The four tiles show totals and open the matching lists | D15: Functional | E15: High | F15: Any | G15: Any time | I15: Signed in as SAO 990001. | J15: 1. Open Organizations > Agency overview. 2. Read the tiles: Pending reviews, Organizations, Colleges, Archived. 3. Select Pending reviews, read the page, go back. 4. Select Organizations, read the page, go back. 5. Select Colleges, read the page, go back. 6. Select Archived and read the page. | K15: Pending reviews opens Registrations and organizations on the Pending review tab. Organizations opens the Active tab. Colleges opens the Colleges page. Archived opens the Archived tab. The numbers on the tiles match the tab counts. | M15: Not run
A16: SAO-015 | B16: Organizations > Agency overview | C16: Colleges with work to do come first and each college summarises its organizations | D16: Functional | E16: High | F16: Laptop | G16: Any time | I16: Signed in as SAO 990001. A semester must be active first (Setup and records > Academic years, Set as active). Department Head 940001 has registered a new organization that is still Pending review. | J16: 1. Open Organizations > Agency overview. 2. Read the summary line of each college header. 3. Check which college is listed first. 4. Select the arrow button on a college header to close it, then open it again. 5. Find the pending organization inside its college. | K16: Each college header reads like "1 organization · 1 pending · 0 active · 0 returned · 0 archived" (plus "n awaiting administrator" when an approved organization has no administrator). Colleges that need review are listed first and start open; quiet colleges come later. Inside a college the pending registration sits above organizations with "Nothing waiting". The arrow button opens and closes the list. | M16: Not run
A17: SAO-016 | B17: Organizations > Agency overview | C17: Each organization row offers only the actions that fit its status | D17: Functional | E17: High | F17: Any | G17: Any time | I17: Signed in as SAO 990001. One Pending, one Active organization with no administrator, and one Archived organization exist (use the registration journey to create them). | J17: 1. Open Organizations > Agency overview and find a Pending row. 2. Select Review on it, read the drawer, then close it. 3. Find an Active row with no administrator and select Provision administrator. 4. Go back and select Open on any row. 5. Find an Archived row and read its badge. | K17: Review appears only on Pending rows and opens the Review registration drawer. Provision administrator appears only on Active rows with no administrator and opens the Create administrator form for that organization. Open appears on every row and shows the Organization overview. The column Needs attention reads "Nothing waiting" or for example "1 approval, 2 documents". Archived rows show the badge "Archived, read only". | M17: Not run
A18: SAO-017 | B18: Organizations > Registrations and organizations | C18: The four tabs show counts and open on the right default | D18: Functional | E18: High | F18: Any | G18: Any time | I18: Signed in as SAO 990001. | J18: 1. Open Organizations > Registrations and organizations. 2. Read the four tab names and the number in brackets on each. 3. Select each tab in turn. 4. Read one card: name, code, college, status badge, members and admins. 5. Look at the address bar after each tab. | K18: Tabs read Pending review (n), Active (n), Returned (n) and Archived (n). The page opens on the first tab that has items in the order Pending, Returned, Active, Archived. The address shows ?status=pending, active, returned or archived. Cards are grouped under a college heading. A card shows the name, "ACRONYM · College", a status badge, and "N members · N admins". Pending cards also show "Submitted <date>". | M18: Not run
A19: SAO-018 | B19: Organizations > Registrations and organizations | C19: Search narrows the list and each tab has its own empty message | D19: Functional | E19: Medium | F19: Any | G19: Any time | I19: Signed in as SAO 990001. | J19: 1. On the Active tab type PSITS in Search organizations. 2. Clear it and type the name of a college, for example Business. 3. Clear it and type zzzz. 4. Read the empty message, then clear the search. 5. Open a tab that has no items (Pending review, Returned or Archived) and read its message. | K19: The placeholder reads "Name, code, or college". After a short pause the list shows only matching organizations (name, code or college). Searching zzzz shows "No active student organizations match this view." with "Try a different search term." Empty tabs say: Pending "No organizations are waiting for review."; Returned "No organizations are returned to their Department Head."; Archived "No archived organizations." each with a short hint line. | M19: Not run
A20: SAO-019 | B20: Organizations > Registrations and organizations | C20: The Review registration drawer shows the registration and its ten documents | D20: Functional | E20: High | F20: Any | G20: Any time | I20: Signed in as SAO 990001. A semester must be active first (Setup and records > Academic years, Set as active). Department Head 940001 has registered an organization with all ten files. | J20: 1. Open the Pending review tab. 2. Select Review on the new organization. 3. Read the drawer titled Review registration. 4. Scroll to Registration documents. 5. Select Open on the first document. | K20: The drawer shows the registration steps, Organization (name and code), College, Description, Submitted date and Submitted by. Registration documents lists 10 files, each with an Open button; Open shows the PDF in a new tab. The footer has Return and Approve, and a box Remarks (required to return). Approve stays greyed out while the details load. | M20: Not run
A21: SAO-020 | B21: Organizations > Registrations and organizations | C21: Return without remarks is refused | D21: Validation | E21: High | F21: Any | G21: Any time | I21: Signed in as SAO 990001. A Pending registration exists. | J21: 1. Open Review on a pending organization. 2. Leave Remarks empty. 3. Select Return. 4. Read the message under the Remarks box. 5. Close the drawer and look at the organization. | K21: The message "Add remarks explaining what the Department Head needs to fix." appears under Remarks and nothing is saved. The organization is still in Pending review. | M21: Not run
A22: SAO-021 | B22: Organizations > Registrations and organizations | C22: Return a registration with remarks and the Department Head sees it | D22: Functional | E22: High | F22: Any | G22: Any time | I22: Signed in as SAO 990001. A Pending registration from Department Head 940001 exists. | J22: 1. Open Review on the pending organization. 2. Type "Missing charter signature" in Remarks. 3. Select Return and read the green message. 4. Open the Returned tab and read the card. 5. Log out and sign in as Department Head 940001. 6. Open Organizations and find the row. | K22: The green message reads "<Organization name> returned to its Department Head." The drawer closes and the Pending count goes down by one. On the Returned tab the card shows "Returned with remarks" and your text. The Department Head sees the row as Returned with the SAO remarks and the button Edit and resubmit. | M22: Not run
A23: SAO-022 | B23: Organizations > Registrations and organizations | C23: Approve a registration and move on to give it an administrator | D23: Functional | E23: High | F23: Any | G23: Any time | I23: Signed in as SAO 990001. A Pending registration exists. | J23: 1. Open Review on the pending organization. 2. Select Approve and read the green message. 3. Read the next step shown in the drawer. 4. Select Provision administrator. 5. Read the Create administrator form. 6. Open the Active tab and find the organization. | K23: The message reads "<Organization name> approved and activated." The drawer stays open and says "Provision an administrator" with the text that the organization cannot sign in until it has one. Provision administrator opens Organizations > Administrators with the Create administrator form and the organization locked. On the Active tab the card shows Active and "0 admins". The Pending count drops by one. | M23: Not run
A24: SAO-023 | B24: Organizations > Registrations and organizations | C24: A registration that was already decided cannot be decided again | D24: Negative | E24: Medium | F24: Laptop | G24: Any time | I24: Signed in as SAO 990001. Two browser windows. A Pending registration exists. | J24: 1. In window A and window B, open Review on the same pending organization. 2. In window A select Approve. 3. In window B type some remarks and select Return (or select Approve). 4. Read the red message in window B. 5. Look at the Pending review tab in window B. | K24: Window B shows the red message "Only a pending registration can be reviewed." The drawer closes and the lists refresh. The organization stays Active; the second decision is not applied. | M24: Not run
A25: SAO-024 | B25: Organizations > Registrations and organizations | C25: Edit an active organization | D25: Functional | E25: High | F25: Any | G25: Any time | I25: Signed in as SAO 990001. Use an organization that is safe to change (not PSITS-CCS), for example one made in the registration journey. | J25: 1. Open the Active tab and find the organization card. 2. Select the actions menu (Organization actions) and choose Edit organization. 3. Change the Description and pick a new Organization color. 4. Select Save organization. 5. Read the green message and the card. | K25: The dialog Edit organization has Organization name, Organization code, Main organization, College (read only), Organization color, Organization logo (optional) and Description. After saving, "Organization updated." appears and the card shows the new description and colour stripe. | M25: Not run
A26: SAO-025 | B26: Organizations > Registrations and organizations | C26: Edit organization refuses empty and duplicate values | D26: Validation | E26: Medium | F26: Any | G26: Any time | I26: Signed in as SAO 990001. At least two active organizations exist. | J26: 1. Open Edit organization on an active organization. 2. Clear Organization name and select Save organization. 3. Type the name back. Change Organization code to the code of another organization. 4. Select Save organization and read the red message. 5. Set Organization name to the exact name of another organization and save again. 6. Cancel and look at the card. | K26: An empty name is stopped by the browser ("Please fill out this field") and nothing is sent. A duplicate code or name shows a red message such as "The acronym has already been taken." or "The name has already been taken." and the dialog stays open. After Cancel the card is unchanged. | L26: VERIFY: exact wording of the duplicate messages. | M26: Not run
A27: SAO-026 | B27: Organizations > Registrations and organizations | C27: Add an existing user to an organization and manage its user profiles | D27: Functional | E27: Medium | F27: Laptop | G27: Any time | I27: Signed in as SAO 990001. A user from the same college who belongs to another organization exists (if none, only the empty result can be tested). | J27: 1. On the Active tab open the actions menu of an organization and choose Add existing user. 2. Read the note under the organization name and type a School ID in Search existing users. 3. Choose the user, pick a Role in destination organization, and select Add user. 4. Open the actions menu again and choose Manage user profiles. 5. Search for a School ID. Select Delete profile on a throwaway profile only, then read the confirmation box and cancel. | K27: The note reads "College: <name>. Only eligible users from this college who are not already members are listed." With no match it says "No eligible users found in this college." Roles offered: Student, SBO Officer, Department Head, Admin. A successful add shows "User added to the organization." Manage user profiles lists "Name · School ID", "Organization · role · status" and "Primary profile" or "Additional profile". Delete profile asks you to type the School ID to confirm; a profile that cannot be removed shows a reason and its button is greyed. With no match: "No profiles found in the organizations you manage." | M27: Not run
A28: SAO-027 | B28: Organizations > Registrations and organizations | C28: Archive an active organization | D28: Functional | E28: High | F28: Any | G28: Any time | I28: Signed in as SAO 990001. Use a throwaway organization (not PSITS-CCS), because its members cannot sign in while it is archived. | J28: 1. On the Active tab open the actions menu of the throwaway organization. 2. Choose Archive organization. 3. Read the dialog and type a short Reason (optional). 4. Select Archive organization. 5. Read the green message. 6. Open the Archived tab and read the note at the top. | K28: The dialog says "<Name> becomes read-only and its members can no longer sign in. You can restore it later." After confirming, "<Name> archived." appears. The organization leaves the Active tab and shows on the Archived tab with the note "Archived organizations are read-only. Restore to make changes." and the badge "Archived, read only". | M28: Not run
A29: SAO-028 | B29: Organizations > Registrations and organizations | C29: An archived organization is read only everywhere until it is restored | D29: Access | E29: High | F29: Any | G29: Any time | I29: Signed in as SAO 990001. An archived organization with an administrator exists. | J29: 1. On the Archived tab read the buttons on the card. 2. Try to sign in as the organization administrator in another window. 3. Sign in as Department Head 940001 and look at the row on Organizations. 4. As SAO select Restore on the card and confirm Restore organization. 5. Read the green message and the Active tab. 6. Sign in as the organization administrator again. | K29: The card has only Open and Restore (no Review, Edit or Archive). The administrator cannot sign in and sees a clear message (VERIFY wording). The Department Head sees the row as Archived, Read only, with only View checklist. After restoring, "<Name> restored." appears, the organization is back on Active, and the administrator can sign in. | M29: Not run
A30: SAO-029 | B30: Organizations > Registrations and organizations | C30: On a phone the organization lists turn into cards and nothing is cut off | D30: Usability | E30: Medium | F30: Phone | G30: Any time | I30: Signed in as SAO 990001. Use a phone or a window narrower than 768 pixels. | J30: 1. Open Organizations > Agency overview. 2. Scroll to a college and read a row. 3. Open Registrations and organizations and open Review on a card. 4. Scroll the drawer to the bottom buttons. 5. Open Reviews > Compliance and read the Accreditation tab. | K30: Rows appear as readable cards, every button is large enough to tap, the Return and Approve buttons are reachable at the bottom of the drawer, and the page never scrolls sideways. | M30: Not run
A31: SAO-030 | B31: Organizations > Registrations and organizations > Open (Organization overview) | C31: The overview page shows one organization at a glance | D31: Functional | E31: High | F31: Laptop | G31: Any time | I31: Signed in as SAO 990001. Use PSITS-CCS. | J31: 1. Open Organizations > Agency overview and select Open on PSITS-CCS. 2. Read the heading, status and the registration steps. 3. Scroll through Leadership, Members by role, Events, Approved budgets, Compliance and Pending approvals. 4. Select Open the review queue, then go back. 5. Select Open on a document in Latest documents. 6. Select View all documents and then Back to agency overview. | K31: The page shows the name, "ACRONYM · College", a status badge and steps Registered, SAO review, Administrator, First use. Leadership lists people with positions and status. Members by role shows Students, SBO officers, Admins and Total. Events shows Upcoming and Recent ("None." when empty). Approved budgets shows Allocated, Spent, Income, Remaining and "N approved budgets. Only approved budgets are counted." Compliance shows the accreditation badge and Documents awaiting review. Pending approvals says how many requests wait. Open the review queue opens Compliance, Review queue tab; View all documents opens the Track documents tab; a document opens in a new tab; with none: "No documents have been submitted." | M31: Not run
A32: SAO-031 | B32: Organizations > Registrations and organizations > Open (Organization overview) | C32: An organization that does not exist shows an error with a way back | D32: Negative | E32: Low | F32: Any | G32: Any time | I32: Signed in as SAO 990001. | J32: 1. Replace the address end with /dashboard/super-admin/organizations/999999 and press Enter. 2. Read the message. 3. Select Back to agency overview. | K32: The page shows "Organization unavailable" with an error description and a Retry button. The link Back to agency overview returns to the Agency overview. | L32: VERIFY: description wording. | M32: Not run
A33: SAO-032 | B33: Organizations > Administrators | C33: The administrator list and its three summary tiles | D33: Functional | E33: High | F33: Any | G33: Any time | I33: Signed in as SAO 990001. | J33: 1. Open Organizations > Administrators. 2. Read the three tiles: Total Admins, Active Accounts, Organizations Covered. 3. Read the table columns and one row. 4. Look for the grey group headings between rows. 5. Find School IDs 900001, 920011, 990002 and 990032 in the table. | K33: Tiles show counts. The table columns are Administrator (name, then "email · School ID"), Organization (the code), Position ("Organization Admin" when none is set), Status and Action (a menu). Group headings read "Main organizations" and "Sub organizations". The seeded Admins and Advisers appear as active. | M33: Not run
A34: SAO-033 | B34: Organizations > Administrators | C34: Search and filter the administrator list | D34: Functional | E34: Medium | F34: Any | G34: Any time | I34: Signed in as SAO 990001. | J34: 1. Type 920011 in the search box (placeholder "Search name, School ID, email, or position"). 2. Clear it. Choose one organization in "Filter by organization". 3. Set "Filter by account status" to Inactive. 4. Read the result. 5. Set the status back to All statuses and choose All organizations. | K34: Each filter narrows the table. When nothing matches the table is replaced by "No administrator accounts match this view." with "Change the filters or create a new Admin user." Clearing the filters brings the rows back. Status options are All statuses, Active, Inactive and Disabled. | M34: Not run
A35: SAO-034 | B35: Organizations > Administrators | C35: Create an administrator who must change the password at first sign in | D35: Functional | E35: High | F35: Laptop | G35: Any time | I35: Signed in as SAO 990001. An Active organization exists (for example one just approved). | J35: 1. Select New Admin User. 2. Fill School ID (an unused number up to 8 digits, for example 9100123), First name, Last name and a new Email address. 3. Optionally fill Contact number and Position title (for example President). 4. Choose the Assigned organization. 5. Type the same Password and Confirm password (8 or more characters). 6. Select Create Admin User. 7. Read the green message and find the new row. 8. Sign in as the new administrator. | K35: The dialog closes and the green message reads "New Admin user created with the password set by SAO." The new administrator appears with status active. A box says "Done: <name> can sign in" with the button Open organization. The new administrator signs in with that password and must choose a new one before anything else opens, then reaches the Admin dashboard. | M35: Not run
A36: SAO-035 | B36: Organizations > Administrators | C36: The create form refuses missing, mismatched and bad values | D36: Validation | E36: High | F36: Any | G36: Any time | I36: Signed in as SAO 990001. | J36: 1. Select New Admin User and select Create Admin User with an empty form. 2. Fill every required field but type a different Confirm password. Select Create Admin User. 3. Make the passwords match but only 5 characters long and select Create Admin User. 4. Type abc (no @) in Email address and select Create Admin User. 5. Type 0 in School ID, then 100000000, and select Create Admin User each time. 6. Use an existing School ID such as 900001 and select Create Admin User. 7. Use a new School ID but an existing email and select Create Admin User. | K36: The browser stops an empty form and highlights the first empty field. Different passwords show the red message "Password confirmation does not match." A 5 character password, an email without @ and a School ID outside 1 to 99999999 are stopped by the browser. An existing School ID or email shows a red message such as "The school id has already been taken." or "The email has already been taken." (VERIFY wording). The dialog stays open and no account is created. | M36: Not run
A37: SAO-036 | B37: Organizations > Administrators | C37: Only active organizations can be chosen, and a provisioning link locks the choice | D37: Validation | E37: Medium | F37: Laptop | G37: Any time | I37: Signed in as SAO 990001. A Pending organization and an Active organization with no administrator exist. | J37: 1. Select New Admin User and open the Assigned organization list. 2. Check that Pending, Returned and Archived organizations are not listed. 3. Close the form. On Registrations and organizations select Provision administrator on the Active organization. 4. Check the Assigned organization field and the text under it. 5. Replace the address with /dashboard/super-admin/admins?organization=<id of the Pending organization>&create=1 and press Enter. 6. Read the red message. | K37: The list offers only active organizations as "ACRONYM: Name". With Provision administrator the field is greyed and says "Locked to the organization you are provisioning." For a pending organization the page says "<Name> is not active yet. Approve its registration before assigning an administrator." and no form opens. | M37: Not run
A38: SAO-037 | B38: Organizations > Administrators | C38: Edit an administrator | D38: Functional | E38: High | F38: Any | G38: Any time | I38: Signed in as SAO 990001. Use Admin 900002 or an administrator you created. | J38: 1. Open the Action menu of the row and choose Edit administrator. 2. Check that School ID cannot be changed and that there is no password field. 3. Change Position title. 4. Select Save Changes. 5. Read the green message and the row. | K38: The dialog is titled Edit Admin User and shows the School ID as plain text. There is no password field (the SAO cannot set an administrator password). After saving, "Administrator account updated successfully." appears and the Position column shows the new title. | M38: Not run
A39: SAO-038 | B39: Organizations > Administrators | C39: The last active administrator of an organization cannot be switched off | D39: Negative | E39: High | F39: Any | G39: Any time | I39: Signed in as SAO 990001. Organization NSC-CHS has only one Admin, Adviser 990032. | J39: 1. Find School ID 990032 and open Edit administrator. 2. Set Account status to Disabled. 3. Select Save Changes and read the red message. 4. Set Account status back to Active, then choose a different Assigned organization. 5. Select Save Changes and read the message again. | K39: Both attempts show the red message "Add another active administrator before transferring or deactivating this organization's last active administrator." The account stays active and in its organization. | M39: Not run
A40: SAO-039 | B40: Organizations > Administrators | C40: Send a password reset link to an administrator | D40: Functional | E40: Medium | F40: Any | G40: Any time | I40: Signed in as SAO 990001. Mail is switched off on the public copy, so no email arrives there. | J40: 1. Open the Action menu of an active administrator and choose Reset access. 2. Read the box titled Initiate password reset. 3. Select Send reset link. 4. Read the green message. 5. Open the Action menu of an inactive administrator and look at Reset access and Hand over role. | K40: The box says a secure reset link will be sent to the administrator's registered email and the current password is not shown. After Send reset link the green message reads "Password reset instructions were sent to the administrator email address." (VERIFY wording; on the public copy the mail is only written to the server log). For an inactive administrator Reset access and Hand over role are greyed out. | M40: Not run
A41: SAO-040 | B41: Organizations > Administrators | C41: Hand over the administrator role to an existing member | D41: Functional | E41: High | F41: Laptop | G41: Any time | I41: Signed in as SAO 990001. Use a throwaway organization with an active Admin and a student or officer whose primary organization is the same one. | J41: 1. Open the Action menu of the Admin and choose Hand over role. 2. Read the drawer titled Hand over administrator role. 3. Type the member name in Find a member and pick the member. 4. Select Hand over. 5. Read the message that appears. 6. Sign in as the successor, then try to sign in as the old Admin. | K41: The drawer explains that the successor takes the position and the old account is deactivated, not deleted. The message reads "<Successor> now holds <position>" with "<Old Admin>'s account is inactive; their records stay in <Organization>'s history." The old Admin shows inactive and cannot sign in. The successor now sees the Admin menu. | M41: Not run
A42: SAO-041 | B42: Organizations > Administrators | C42: Hand over to a new account and the checks on that form | D42: Validation | E42: Medium | F42: Laptop | G42: Any time | I42: Signed in as SAO 990001. Use a throwaway organization with an active Admin. | J42: 1. Open Hand over role and choose the tab New account. 2. Check that Hand over is greyed out while fields are empty. 3. Fill School ID, First name, Last name, Email, Initial password and Confirm password, but type a different confirmation. 4. Select Hand over and read the red message. 5. Fix the confirmation. Use an existing School ID and select Hand over. 6. Use a new School ID and select Hand over. 7. Switch to Existing member, search for zzzz and read the text. | K42: Hand over stays greyed out until every field except Contact number is filled. A wrong confirmation or an existing School ID shows a red message in the drawer (VERIFY wording) and nothing changes. A valid form hands the role over and the new account must change its password at first sign in. The member search with no match says "No matching members. Check the spelling, or create a new account for the successor." | M42: Not run
A43: SAO-042 | B43: Organizations > Administrators | C43: Delete an administrator account | D43: Functional | E43: Medium | F43: Any | G43: Any time | I43: Signed in as SAO 990001. Use an administrator you created with no records. | J43: 1. Open the Action menu of that administrator and choose Delete administrator. 2. Read the box. 3. Select Cancel and check the row is still there. 4. Repeat and select Delete administrator. 5. Read the green message. 6. Try the same on an administrator with records such as 900001 and read the result. | K43: The box says "This removes the administrator profile. Accounts with linked records cannot be deleted." Cancel keeps the row. A confirmed delete shows "Administrator account removed." and the row disappears. An administrator with linked records is refused with a red message (VERIFY wording) and stays in the list. | M43: Not run
A44: SAO-043 | B44: Organizations > Administrators | C44: Administrators of an archived organization cannot be changed | D44: Negative | E44: Medium | F44: Any | G44: Any time | I44: Signed in as SAO 990001. An archived organization that still has an administrator exists. | J44: 1. On Administrators find the administrator of the archived organization. 2. Open Edit administrator and change Position title. 3. Select Save Changes and read the red message. 4. Select New Admin User and open the Assigned organization list. | K44: The save is refused with a red message such as "Archived organizations are read only." (VERIFY wording) and nothing changes. The archived organization is not offered in the Assigned organization list. | M44: Not run
... A49: SAO-048 | B49: Organizations > Colleges | C49: Deactivate and reactivate a Department Head | D49: Functional | E49: High | F49: Any | G49: Any time | I49: Signed in as SAO 990001. Use Department Head 940005 (Engineering). Do not use 940001. | J49: 1. Select Manage on the Engineering card and then Deactivate. 2. Read the box titled Deactivate Department Head and select Deactivate. 3. Read the green message and the badge on the card. 4. In another window try to sign in as 940005. 5. Select Manage again and check Send password reset. 6. Select Reactivate and confirm. | K49: The box says they can no longer sign in and any open session ends. The message reads "<Name> was deactivated and can no longer sign in." The badge turns Inactive, the Assign Department Head button appears, and Send password reset is greyed out. The sign in is refused. After Reactivate the message reads "<Name> was reactivated." and the head signs in again. | M49: Not run
A50: SAO-049 | B50: Organizations > Colleges | C50: Upload a college logo | D50: Validation | E50: Low | F50: Any | G50: Any time | I50: Signed in as SAO 990001. | J50: 1. Select Upload logo on one college card and choose a PNG smaller than 2 MB. 2. Read the green message and the card. 3. Select Upload logo again and choose a PDF file. 4. Read the result. 5. Select Upload logo again and choose an image larger than 2 MB. | K50: A good image shows "Logo updated for <College>." and the logo appears on the card. A wrong file type or an image over 2 MB shows a red message and the old logo stays. | L50: VERIFY: the exact message. | M50: Not run
A51: SAO-050 | B51: Reviews > Compliance | C51: The six Compliance tabs open and show their content | D51: Functional | E51: High | F51: Any | G51: Any time | I51: Signed in as SAO 990001. | J51: 1. Open Reviews > Compliance. 2. Read the six tab names. 3. Select each tab in turn. 4. After each tab read the address bar. 5. Look for an error banner on every tab. | K51: Tabs read Accreditation (opens first), Requirements, Review queue (with a number in brackets when submissions wait), Event requirements, Financial reports, Track documents. The address ends with ?tab=accreditation, requirements, review, events, financial or documents. Each tab shows its own content and no error banner. | M51: Not run
A52: SAO-051 | B52: Reviews > Compliance | C52: Accreditation tab ranks organizations by what needs attention | D52: Functional | E52: High | F52: Any | G52: Any time | I52: Signed in as SAO 990001. A semester must be active first (Setup and records > Academic years, Set as active). | J52: 1. Open the Accreditation tab. 2. Read the card title and the academic year line. 3. Read the columns for the first rows. 4. Find a row whose Next action says Review N submission(s) and select it. 5. Read the Review queue that opens. | K52: The card is "Organization accreditation" with "Academic year 2026-2027". Columns are Organization, Accreditation (badge Accredited, Pending review, Incomplete or Returned plus progress steps), Requirements met (for example 3/11), Overdue (red when above 0) and Next action (Review N submissions, Awaiting submission, Waiting on the organization, All caught up, or No active requirements). Organizations with overdue items come first. The button opens the Review queue filtered to that organization with Awaiting review selected. With no data the empty text is "No organizations to track yet". | M52: Not run
A53: SAO-052 | B53: Reviews > Compliance | C53: Add a requirement and see the checks on the form | D53: Validation | E53: High | F53: Any | G53: Any time | I53: Signed in as SAO 990001. A semester must be active first (Setup and records > Academic years, Set as active). | J53: 1. Open the Requirements tab and select New requirement. 2. Select Add requirement with the form empty (clear the Academic year first if it is prefilled). 3. Read the messages. 4. Fill Name (for example QA Test Report), Deadline (a future date) and Academic year. 5. Select Add requirement. 6. Read the green message and find the row. 7. Sign in as Admin 900001 and open Records > Compliance. | K53: The empty form shows "Choose the academic year this requirement applies to.", "Set the deadline for organizations." and "Enter a name for this requirement." and the cursor goes to the first one. A good form shows "Requirement added. Every active organization has been notified." and the row appears in the Requirement catalog (columns Requirement, Academic year, Deadline, Description). Admin 900001 sees a notification "New compliance requirement" and the new requirement in Compliance. | M53: Not run
A54: SAO-053 | B54: Reviews > Compliance | C54: Edit, switch off and delete a requirement | D54: Functional | E54: Medium | F54: Any | G54: Any time | I54: Signed in as SAO 990001. Use the QA Test Report requirement from the previous case. | J54: 1. On the Requirements tab select Edit on the row, change the Name and select Save changes. 2. Switch the toggle named "<name> active" off and read the box. 3. Select Mark inactive and read the message. 4. Switch it on again and read the message. 5. Select Delete, read the box and select Delete requirement. 6. Try Delete on a requirement that already has submissions. | K54: Save shows "Requirement updated." The box "Mark this requirement inactive?" says organizations will no longer need to submit it; after confirming the message reads "<name> marked inactive." and switching on shows "<name> marked active." with no box. Delete shows "Delete this requirement?" and then "<name> deleted." A requirement with submissions is refused with "This requirement already has submissions. Deactivate it to preserve those records." A requirement of a completed semester cannot be edited ("Completed semester requirements are read only." VERIFY). | M54: Not run
A55: SAO-054 | B55: Reviews > Compliance | C55: Review queue filters, count and empty states | D55: Functional | E55: High | F55: Any | G55: Any time | I55: Signed in as SAO 990001. | J55: 1. Open the Review queue tab and read the count above the table. 2. Open "Filter by status" and try Awaiting review, Approved, Returned and All statuses. 3. Open "Filter by organization" and choose one organization. 4. Choose a combination that has no rows and read the message. 5. Select Clear filters. | K55: The default status is Awaiting review. The count reads "N submissions" or "1 submission". Columns are Organization, Requirement (with Registration document, Renewal document or Semestral report), Submitted, Submitted by, Status. A filter with no rows shows "No submissions match these filters" with "Try a different status or organization, or clear the filters." Clear filters returns to Awaiting review. With nothing at all the page says "Nothing to review". The organization list also holds registrations written as "<Name> (registration)". | M55: Not run
A56: SAO-055 | B56: Reviews > Compliance | C56: Approve a compliance submission | D56: Functional | E56: High | F56: Any | G56: Any time | I56: Signed in as SAO 990001. Admin 900001 has uploaded one requirement on Records > Compliance (PDF file). | J56: 1. Open the Review queue tab and find the submission. 2. Select the open icon on the row to read the file. 3. Select the organization name in the row to open the drawer. 4. Select Approve. 5. Read the box and select Approve. 6. Read the message, then open the Accreditation tab. | K56: The file opens in a new tab. The drawer shows the steps and "Submitted by". The box "Approve this submission?" says the organization will be notified and the document will be locked. The message reads Approved "<requirement>" for <organization>. The drawer status becomes Approved and Approve and Return disappear. On Accreditation the Requirements met value for that organization goes up by 1. Admin 900001 sees it as Approved and cannot upload again. | M56: Not run
A57: SAO-056 | B57: Reviews > Compliance | C57: Return a compliance submission needs remarks | D57: Validation | E57: High | F57: Any | G57: Any time | I57: Signed in as SAO 990001. A submission is waiting in the Review queue. | J57: 1. Open the submission drawer and select Return. 2. Select Return to organization with the Remarks box empty. 3. Read the message. 4. Type what must be fixed in Remarks. 5. Select Return to organization. 6. Read the message and the drawer. | K57: The box is titled Return this submission ("A remark is required so the organization knows what to fix."). The empty box shows "Write what the organization needs to correct before returning this submission." A good return shows "Submission returned to the organization with your remarks." The status becomes Returned and the drawer shows "SAO remarks". Admin 900001 sees the remark and can upload a new file. | M57: Not run
A58: SAO-057 | B58: Reviews > Compliance | C58: Registration documents are not decided in the Review queue | D58: Negative | E58: Medium | F58: Any | G58: Any time | I58: Signed in as SAO 990001. A Pending registration exists. | J58: 1. Open the Review queue tab. 2. Set Filter by status to All statuses and choose "<Organization> (registration)" in Filter by organization. 3. Read the Status text of a row. 4. Check the row for Approve and Return buttons. 5. Select Open organization review. | K58: Registration documents show the text "Decided in the organization review" (or "Registration returned, waiting for the Department Head" for a returned one). There are no Approve or Return buttons. Open organization review opens the Review registration drawer in Registrations and organizations. A second SAO window that approves the same submission first causes "Only a pending submission can be reviewed." in the first window (VERIFY). | M58: Not run
A59: SAO-058 | B59: Reviews > Compliance | C59: Event requirements checklist: add, edit and remove a file requirement | D59: Functional | E59: Medium | F59: Any | G59: Any time | I59: Signed in as SAO 990001. A semester must be active first (Setup and records > Academic years, Set as active). | J59: 1. Open the Event requirements tab and read the card Submission checklist. 2. Select Add requirement with File name empty and read the message. 3. Type QA sample letter, choose Venue type On campus and select Add requirement. 4. Select the pencil on the new row, change the name and select Save changes. 5. Select Remove on the row and read the box. 6. Select Remove requirement. | K59: The checklist shows rows with "PDF · On campus · Required" and the count "N active". The empty form shows "Enter the name of the file organizations must submit." Adding shows "Requirement added." Editing shows "Requirement updated." Removing asks "Remove this requirement?" and then shows "Requirement removed." A requirement that already has submitted files is refused with a red message and must be marked inactive instead. The option "Only if applicable" shows the row as "If applicable". | M59: Not run
A60: SAO-059 | B60: Reviews > Compliance | C60: Approve an event that waits for the SAO | D60: Functional | E60: High | F60: Any | G60: Any time | I60: Signed in as SAO 990001. Admin 900001 proposed an event and uploaded all required files, and Department Head 940001 approved it first. | J60: 1. Open the Event requirements tab and scroll to Events waiting for SAO. 2. Select View files on the event and read the file list. 3. Select Hide files. 4. Select Approve. 5. Read the box and select Approve event. 6. Read the message. | K60: The card shows the event title and "Event #id · requester". View files lists the uploaded files. The box "Approve this event?" says the organization will be notified. The message reads "Event approved." and the row leaves the list. With nothing waiting the card says "No event submissions are waiting for review." Before the Department Head approves, the SAO cannot decide: "The Department Head must approve this event before the SAO can decide it." (VERIFY where it shows). | M60: Not run
A61: SAO-060 | B61: Reviews > Compliance | C61: Reject an event needs remarks | D61: Validation | E61: High | F61: Any | G61: Any time | I61: Signed in as SAO 990001. An event waits for the SAO as in the previous case. | J61: 1. Under Events waiting for SAO select Reject. 2. Select Reject event with Remarks for rejection empty. 3. Read the message. 4. Type why the event is rejected. 5. Select Reject event. 6. Read the message. | K61: The box is titled Reject this event. The empty box shows "Write why this event is rejected so the organization can respond." A good rejection shows "Event rejected." and the organization sees the remarks on the event. | M61: Not run
A62: SAO-061 | B62: Reviews > Compliance | C62: Financial reports tab: search, filters and empty state | D62: Functional | E62: Medium | F62: Any | G62: Any time | I62: Signed in as SAO 990001. | J62: 1. Open the Financial reports tab and read the line under the tabs. 2. Type part of a report title in "Search report titles". 3. Choose an organization, then a Document type, then a Report status. 4. Read the result count and the filter chips. 5. Choose filters that match nothing and read the message. 6. Select Clear. | K62: The tab says "Reports organizations submitted for SAO review. Decide each one here." The Report inbox says only reports that completed Department Head review appear here. Options: Document type (All document types, Financial reports, Income statements); Report status (All statuses, Awaiting SAO review, Approved, Rejected). The count reads "N financial reports". Status shows as "pending sao", "approved" or "rejected". No match shows "No financial reports found." Clear restores the list. | M62: Not run
... A65: SAO-064 | B65: Reviews > Compliance | C65: Track documents: find any file an organization submitted | D65: Functional | E65: High | F65: Any | G65: Any time | I65: Signed in as SAO 990001. Organizations have submitted files. | J65: 1. Open the Track documents tab. 2. Type an organization code in Search organizations. 3. Choose a Semester and a Document type. 4. Select an organization row to open it. 5. Select View on a file. 6. Select Clear filters. | K65: Rows read "CODE - Name", the college, "N files" and "Latest <date>". An open row groups files under Event requirements, Semestral report, Semester renewal, Financial reports, Financial report supporting documents and Registration documents, each with a status badge and, for events, "With the Department Head" or "With the SAO". View opens the file in a new tab. "Showing x of y files" and Load more files appear for long lists. No match shows "No documents match these filters". With no files at all: "No documents submitted yet." Lists show 20 organizations per page. | M65: Not run
A66: SAO-065 | B66: Reviews > Venues | C66: Venues page has three tabs and a working calendar | D66: Functional | E66: High | F66: Any | G66: Any time | I66: Signed in as SAO 990001. | J66: 1. Open Reviews > Venues. 2. Read the three tabs: Calendar, Booking requests, Venue catalog. 3. On the Calendar select Next, then Previous, then Today. 4. Open "Venue to show" and choose one venue. 5. Switch the calendar view if the page offers a Day, Week or Month choice. | K66: Calendar is selected first. The card says "Who holds each venue and when. A pending request that overlaps another booking is labelled Conflict." Next and Previous move the period, Today comes back, and the Venue to show list narrows the calendar. On a phone the calendar does not scroll sideways. | L66: VERIFY: the names of the view buttons. | M66: Not run
A67: SAO-066 | B67: Reviews > Venues | C67: Add a venue and see the form checks | D67: Validation | E67: High | F67: Any | G67: Any time | I67: Signed in as SAO 990001. | J67: 1. Open the Venue catalog tab and select New venue. 2. Select Add venue with the form empty. 3. Read the red message. 4. Type Name QA Hall, Location "Building A, Ground Floor" and Capacity -1, then select Add venue. 5. Change Capacity to 50 and select Add venue. 6. Read the message and find the row. | K67: The empty form and a negative capacity show "Complete the name, location, and a valid capacity before saving." A good form shows "Venue added to the catalog." and the row appears with Venue, Location, Capacity and an Active status switch. With no venues at all the tab says "No venues added yet". | M67: Not run
A68: SAO-067 | B68: Reviews > Venues | C68: Edit, switch off and delete a venue | D68: Functional | E68: Medium | F68: Any | G68: Any time | I68: Signed in as SAO 990001. Use the QA Hall venue. | J68: 1. On the Venue catalog tab select Edit on QA Hall, change the Capacity and select Save changes. 2. Select the Active switch of QA Hall. 3. Read the message. 4. Select the trash button named "Delete QA Hall", read the box and select Cancel. 5. Select the trash button again and select Delete venue. 6. Try Delete on a venue that has any booking. | K68: Saving shows "Venue updated." The switch shows "QA Hall" marked inactive. and an inactive venue is no longer offered when an organization books (check with Admin 900001, VERIFY). The delete box says it cannot be undone. A confirmed delete shows "QA Hall" deleted. A venue with any booking, even a past or declined one, is refused: "This venue has booking history, so it cannot be deleted. Mark it inactive instead to stop new requests." | M68: Not run
A69: SAO-068 | B69: Reviews > Venues | C69: Booking requests queue: default view, filters and empty states | D69: Functional | E69: High | F69: Any | G69: Any time | I69: Signed in as SAO 990001. | J69: 1. Open the Booking requests tab. 2. Read the status filter and the count (for example "2 requests"). 3. Try each status: Awaiting decision, Approved, Rejected, Withdrawn, All statuses. 4. Choose one venue in "Filter by venue". 5. Choose filters with no result and read the message, then select Clear filters. | K69: The default is Awaiting decision. Columns are Organization, Venue, Event, Requested time, Status (with a stage line). With nothing waiting the page says "Nothing to review" and "Organization admins and officers request venues from Venue booking. Each request appears here for your decision." A filter with no result shows "No booking requests match these filters". Clear filters returns to Awaiting decision. | M69: Not run
A70: SAO-069 | B70: Reviews > Venues | C70: Approve a booking request and see overlaps first | D70: Functional | E70: High | F70: Any | G70: Any time | I70: Signed in as SAO 990001. Admin 900001 requested a venue on Venue booking. | J70: 1. On Booking requests find the pending row. 2. Select the organization name to open the drawer, then read it. 3. Select Approve. 4. Read the box titled Approve this booking?. 5. Select Approve in the box. 6. Read the message, then open the Calendar tab. | K70: The drawer shows the booking steps, Organization, Event and Requested time. The box first says "Checking for overlapping bookings..." and then "No overlapping bookings for this venue and time." or lists "Overlaps N other booking(s) for this venue". The message reads Booking for "<venue>" approved., the row leaves Awaiting decision, shows under Approved and appears on the calendar. Admin 900001 sees it approved. Back to back bookings do not overlap. | M70: Not run
A71: SAO-070 | B71: Reviews > Venues | C71: Reject a booking request needs remarks | D71: Validation | E71: High | F71: Any | G71: Any time | I71: Signed in as SAO 990001. A booking request is pending. | J71: 1. Select Reject on the pending row. 2. Read the box titled Reject this booking. 3. Check that Reject booking is greyed out while Remarks is empty. 4. Type the reason in Remarks. 5. Select Reject booking. 6. Read the message. | K71: The box says "A remark is required so the organization knows why." The button is greyed until a reason is typed. The message reads Booking for "<venue>" rejected. and the organization sees the remark. | M71: Not run
A72: SAO-071 | B72: Reviews > Venues | C72: Two requests for the same time are flagged as a Conflict | D72: Negative | E72: Medium | F72: Laptop | G72: Any time | I72: Signed in as SAO 990001. Two organizations (for example Admin 900001 and Admin 920011) each requested the same venue for overlapping times. | J72: 1. Open the Booking requests tab. 2. Look at the Status of both rows. 3. Approve the first request. 4. Select Approve on the second request and read the box. 5. Select Approve in the box. 6. Read the message. | K72: Both rows carry the label Conflict. The second Approve box warns "Overlaps 1 other booking for this venue" and says the server refuses an approval that overlaps an approved booking. The approval is refused with a message such as "Another booking for this venue was approved for an overlapping time in the meantime." (VERIFY wording) and the request stays pending. | M72: Not run
A73: SAO-072 | B73: Reviews > Grievances | C73: Grievance tiles and filters | D73: Functional | E73: High | F73: Any | G73: Any time | I73: Signed in as SAO 990001. Some grievances exist (a Student files one on Support > My grievances). | J73: 1. Open Reviews > Grievances. 2. Read the eight tiles: Submitted, Under review, Resolved, Dismissed, Critical, High, Medium, Low. 3. Select the Submitted tile, then select it again. 4. Use the four filters: Addressed to, Status, Urgency, Category. 5. Sort the table by selecting the Urgency and Filed headers. 6. Select Clear filters. | K73: Selecting a tile highlights it and filters the table; selecting it again clears it. Addressed to offers "Organization + SAO", "Addressed to organizations" and "Addressed to SAO". Category offers Safety & Security, Financial Integrity, Facilities & Maintenance, Academic / Faculty and General. The count reads "N grievances". The default order is by urgency, Critical first. No match shows "No grievances match these filters"; with no data at all: "Nothing to review" with "Students file grievances from My grievances, addressed to their organization or to the SAO. Each one appears here, sorted by urgency." | M73: Not run
A74: SAO-073 | B74: Reviews > Grievances | C74: Open a grievance addressed to the SAO | D74: Functional | E74: High | F74: Any | G74: Any time | I74: Signed in as SAO 990001. Student 2100142 filed a grievance addressed to the SAO (Support > My grievances). | J74: 1. On Grievances select the grievance title. 2. Read the badges at the top of the drawer. 3. Read the steps and the line under them. 4. Read the filer, Addressed to, Description and Filed date. 5. Read the buttons under Update status. | K74: The drawer shows status, "<urgency> urgency" and category badges, the progress steps with a "waiting for SAO" line, the filer's name, Addressed to "Student Affairs Office", the Description and the Filed date. For a grievance filed anonymously toward the organization the SAO still sees the name with the note "Filed anonymously toward the organization. Handle with added discretion." Buttons: Move to under review, Resolve, Dismiss. | M74: Not run
A75: SAO-074 | B75: Reviews > Grievances | C75: Move a grievance to under review | D75: Functional | E75: High | F75: Any | G75: Any time | I75: Signed in as SAO 990001. A grievance with status Submitted exists. | J75: 1. Open the grievance drawer. 2. Select Move to under review. 3. Read the green message. 4. Look at the status badge and at the buttons. 5. Sign in as the student who filed it and open Support > My grievances. | K75: No remarks are needed. The message reads "Grievance updated. The student has been notified." The status becomes Under review and only Resolve and Dismiss remain (it cannot go back to Submitted). The student sees the new status. | M75: Not run
A76: SAO-075 | B76: Reviews > Grievances | C76: Resolve a grievance with remarks | D76: Validation | E76: High | F76: Any | G76: Any time | I76: Signed in as SAO 990001. A grievance with status Submitted or Under review exists. | J76: 1. Open the grievance drawer and select Resolve. 2. Read the box. 3. Check that the Resolve button in the box is greyed out while Remarks is empty. 4. Type the outcome in Remarks. 5. Select Resolve in the box. 6. Read the drawer, then sign in as the student and open My grievances. | K76: The box says "These remarks are shared with the student who filed this grievance." Resolve is greyed until remarks are typed. The message reads "Grievance updated. The student has been notified." The drawer shows Resolved, the Remarks box and "This grievance is closed and cannot be reopened." The student sees Resolved and the remarks. | M76: Not run
A77: SAO-076 | B77: Reviews > Grievances | C77: Dismiss a grievance and confirm it stays closed | D77: Negative | E77: Medium | F77: Any | G77: Any time | I77: Signed in as SAO 990001. A grievance with status Submitted exists. | J77: 1. Open the grievance drawer and select Dismiss. 2. Check that the red Dismiss button is greyed out while Remarks is empty. 3. Type the reason and select Dismiss in the box. 4. Read the drawer. 5. Close and open the same grievance again. | K77: After dismissing, the status is Dismissed with the remarks and the line "This grievance is closed and cannot be reopened." There are no Update status buttons, also after reopening. | M77: Not run
A78: SAO-077 | B78: Reviews > Grievances | C78: A grievance addressed to an organization can also be decided by the SAO | D78: Access | E78: Medium | F78: Any | G78: Any time | I78: Signed in as SAO 990001. A student filed a grievance addressed to their organization. | J78: 1. Set "Filter by addressed to" to Addressed to organizations. 2. Open the grievance. 3. Read Addressed to and the steps. 4. Select Move to under review. | K78: The row subtitle shows the category and the organization name, and the drawer says Addressed to "<Organization name>". The steps show that the Admin's turn comes first (VERIFY wording). The SAO may still move it to Under review and the student is notified. | M78: Not run
A79: SAO-078 | B79: Reviews > Clearances | C79: Clearances page without any period | D79: Functional | E79: Medium | F79: Any | G79: Any time | I79: Signed in as SAO 990001. No clearance period exists yet (skip if one exists). | J79: 1. Open Reviews > Clearances. 2. Read the empty message. 3. Select New clearance period in the message. 4. Select Cancel. | K79: The page says "No clearance periods yet" with "Open a clearance period to generate a pending signature line for every active student, for each role you require." and a New clearance period button. | L79: VERIFY: whether the fresh seed already has a period. | M79: Not run
A80: SAO-079 | B80: Reviews > Clearances | C80: Open a clearance period for every student | D80: Functional | E80: High | F80: Any | G80: Any time | I80: Signed in as SAO 990001. Student accounts exist. | J80: 1. Select New clearance period. 2. Type the Title "QA Clearance 1st Sem" and check that Academic year is filled (for example 2026-2027). 3. Pick a Deadline date. 4. Select the roles "Student Affairs Office (SAO)" and "Organization adviser". 5. Type "Org Secretary" in the extra role box and select Add. 6. Select Open this period. 7. Read the message and the new card. 8. Sign in as Student 2100142 and open Support > My clearance. | K80: The button reads Open this period and is greyed out until Title, Academic year and at least one role are set. The message reads "Clearance period opened. Every active student now has a signature line waiting." The card shows the title, "2026-2027 · Deadline <date>", a badge per role and a meter "Students fully cleared". The student gets the notification "New clearance period opened" and sees the lines. | M80: Not run
A81: SAO-080 | B81: Reviews > Clearances | C81: New clearance period form checks | D81: Validation | E81: Medium | F81: Any | G81: Any time | I81: Signed in as SAO 990001. | J81: 1. Open New clearance period and look at the Open this period button. 2. Clear the Academic year field. 3. Select a role, then select the x on its chip. 4. Type a long text (more than 20 characters) in Academic year, add a Title and one role, and select Open this period. 5. Read the message. | K81: The button is greyed out without a Title, an Academic year or a role. The chip x removes a role (button named "Remove <role>"). The extra role box accepts at most 10 roles in total. An Academic year over 20 characters is refused by the server with a red message under the field (VERIFY wording) and no period is created. | M81: Not run
A82: SAO-081 | B82: Reviews > Clearances | C82: View the students of a period and search them | D82: Functional | E82: High | F82: Any | G82: Any time | I82: Signed in as SAO 990001. A clearance period exists. | J82: 1. Select View students on a period card. 2. Read the drawer heading. 3. Type 2100142 in "Search by name or school ID...". 4. Type zzzz and read the message. 5. Clear the search and read one student card. | K82: The drawer shows the title and "2026-2027 · SAO signature line". Each student card shows the name, School ID, progress steps, a stage line and one row per required role; "All cleared" appears when everything is signed. No match shows "No students in this period" with "No student in this period matches this search." Pages hold 20 students. | M82: Not run
A83: SAO-082 | B83: Reviews > Clearances | C83: Clear the SAO signature of a student | D83: Functional | E83: High | F83: Any | G83: Any time | I83: Signed in as SAO 990001. A clearance period exists and Student 2100142 has a pending SAO line. | J83: 1. In the drawer find Student 2100142 and the row "Student Affairs Office (SAO)". 2. Select Clear. 3. Read the box and select Confirm clear. 4. Read the message and the row. 5. Sign in as Student 2100142 and open Support > My clearance. | K83: The box is titled "Clear Student Affairs Office (SAO)" ("The student will be notified that this line is cleared.") and shows "Signing as the Student Affairs Office (SAO) signatory for this student." The message reads "Signature cleared." The row shows cleared with no buttons. The student sees the line cleared and a notification "Your clearance was updated". | M83: Not run
A84: SAO-083 | B84: Reviews > Clearances | C84: Hold a signature with a reason and clear the hold later | D84: Validation | E84: High | F84: Any | G84: Any time | I84: Signed in as SAO 990001. A student with a pending SAO line exists. | J84: 1. Select Hold on the SAO row. 2. Check that Hold this signature is greyed out while Reason is empty. 3. Type "Unpaid organization dues" and select Hold this signature. 4. Read the message and the row. 5. Select Clear hold and confirm. | K84: The box reads "Hold Student Affairs Office (SAO)" and "The student will see this reason and who to follow up with." The message reads "Signature put on hold." The row shows held with "Reason: Unpaid organization dues" and a Clear hold button. After clearing, the row shows cleared. The student sees the reason while it is held. | M84: Not run
A85: SAO-084 | B85: Reviews > Clearances | C85: The SAO can only sign its own line | D85: Access | E85: Medium | F85: Any | G85: Any time | I85: Signed in as SAO 990001. A period that also requires "Organization adviser" exists. | J85: 1. Open View students on that period. 2. Look at the row for Organization adviser on a student. 3. Look at the row for Student Affairs Office (SAO) on the same student. 4. Open the same SAO row in a second window, clear it there, then select Clear in the first window and confirm. | K85: Rows of other roles show only a status badge, with no Clear or Hold button. Only the SAO row has buttons. A line that was already cleared in the other window is refused with "This clearance line has already been cleared." (VERIFY where it shows). | M85: Not run
A86: SAO-085 | B86: Reviews > Clearances | C86: Delete a clearance period | D86: Negative | E86: Medium | F86: Any | G86: Any time | I86: Signed in as SAO 990001. One unsigned period (use the QA period) and one period with a signed line exist. | J86: 1. Select the trash button named "Delete QA Clearance 1st Sem". 2. Read the box, select Cancel, and check the card remains. 3. Select the trash button again and select Delete period. 4. Read the message. 5. Select the trash button on a period with a cleared or held line and select Delete period. | K86: The box says the period and its unsigned rows are removed and this cannot be undone. A confirmed delete shows "QA Clearance 1st Sem" deleted. A period that already has signed entries is refused with "This clearance period already has signed entries and cannot be deleted." and stays. | M86: Not run
A87: SAO-086 | B87: Updates > University announcements | C87: Announcements page when nothing was written yet | D87: Functional | E87: Low | F87: Any | G87: Any time | I87: Signed in as SAO 990001. No official announcement exists yet (skip if one exists). | J87: 1. Open Updates > University announcements. 2. Read the empty message. 3. Select Create official notice. 4. Read the top of the dialog, then select Cancel. | K87: The page says "No official announcements yet" with "Official notices reach every user, organization, or college you choose. Publish one here." and a button Create official notice. The dialog says "Create official SAO announcement" and "Written manually by the SAO Director. AI drafting is not available here." | M87: Not run
A88: SAO-087 | B88: Updates > University announcements | C88: Save a draft, edit it and delete it | D88: Functional | E88: High | F88: Any | G88: Any time | I88: Signed in as SAO 990001. | J88: 1. Select Create official notice. 2. Type a Title and an Announcement text, leave Confirm publish unticked and select Save draft. 3. Read the card. 4. Select Edit draft, change the Title and select Save draft. 5. Select Delete draft on the card. 6. Read the box and select Delete draft. | K88: The card shows "Student Affairs Office · Official", the title, the label DRAFT, the first lines of the text and "N recipients · all users". Edit draft keeps it a draft. The box "Delete this draft?" says it will never be sent and cannot be undone. After deleting, "Draft deleted." appears and the card is gone. | M88: Not run
A89: SAO-088 | B89: Updates > University announcements | C89: Publish an official notice to all users | D89: Functional | E89: High | F89: Any | G89: Any time | I89: Signed in as SAO 990001. | J89: 1. Select Create official notice and type a Title and an Announcement text. 2. Keep Audience scope on "All HIUSA users". 3. Tick Confirm publish and note that the button text changes. 4. Select Publish official notice. 5. Read the card. 6. Sign in as Student 2100142 and open the bell or Updates. | K89: With Confirm publish ticked the button reads Publish official notice (otherwise Save draft). The card shows PUBLISHED and the number of recipients. The student receives a notification titled "SAO Official: <title>". The published card has no Edit draft and no Delete draft. | M89: Not run
A90: SAO-089 | B90: Updates > University announcements | C90: Choose the audience of a notice | D90: Functional | E90: Medium | F90: Any | G90: Any time | I90: Signed in as SAO 990001. | J90: 1. Open Create official notice. 2. Open Audience scope and read all five choices. 3. Choose "Selected organizations" and tick only PSITS-CCS. 4. In Optional role filter tick STUDENT only. 5. Tick Confirm publish and select Publish official notice. 6. Check that Student 2100142 got the notice and Student 2400118 did not. | K90: Choices are All HIUSA users, All organizations, Selected organizations, All departments, Selected departments. Selected organizations shows a checkbox per organization code; Selected departments shows the college names. Role filter offers STUDENT, SBO OFFICER, DEPARTMENT HEAD, ADMIN. The recipient count on the card matches the audience. Only matching accounts get the notification. | M90: Not run
A91: SAO-090 | B91: Updates > University announcements | C91: Notice form checks and schedule rules | D91: Validation | E91: Medium | F91: Any | G91: Any time | I91: Signed in as SAO 990001. | J91: 1. Open Create official notice and select Save draft with Title empty. 2. Choose "Selected organizations", tick none, tick Confirm publish and select Publish official notice. 3. Choose "Selected departments", tick none and select Publish official notice. 4. Set Schedule (optional) to a date in the past and save. 5. Set Schedule to tomorrow and Expires to today and save. 6. Set Schedule to tomorrow and Expires to the day after and save as a draft. | K91: An empty Title is stopped by the browser. The server answers "Choose at least one organization." and "Choose at least one department." (the red message may show on the page behind the dialog; VERIFY where). A past schedule is refused (VERIFY wording). "Expiration must be after the scheduled publish date." appears for the second case. A valid scheduled notice is saved and the card shows SCHEDULED when published with a future date. | M91: Not run
... A94: SAO-093 | B94: Updates > Notifications | C94: The bell at the top shows new notices and opens the related record | D94: Functional | E94: Medium | F94: Any | G94: Any time | I94: Signed in as SAO 990001. | J94: 1. Look at the bell at the top right and read the number badge. 2. Select the bell. 3. Select one notice and read its detail. 4. Select Open related record. 5. Select the bell again and choose Mark all as read. | K94: The badge shows the unread count (9+ when more than nine). The panel says "Notifications" with "N new". A notice shows its full text with Back to notifications and Open related record. Mark all as read shows "All notifications marked as read." and the badge disappears. An empty panel says "No notifications yet". | M94: Not run
A95: SAO-094 | B95: Updates > Notifications | C95: Other roles create SAO notices that lead to the right page | D95: Functional | E95: High | F95: Laptop | G95: Any time | I95: Signed in as SAO 990001. A semester must be active first (Setup and records > Academic years, Set as active). | J95: 1. Sign in as Department Head 940001 and register a new organization with the ten files. 2. Sign in as Admin 900001 and upload one compliance requirement on Records > Compliance. 3. Sign in as the SAO and open the bell. 4. Select the registration notice and note where it lands. 5. Select the compliance notice and note where it lands. | K95: Each action produces a notice for the SAO. The registration notice leads to the Pending review registration or its drawer. The compliance notice leads to the Review queue on Reviews > Compliance. | L95: VERIFY: the exact destination of each notice and that it lands on the exact item. | M95: Not run
A96: SAO-095 | B96: Setup and records > Academic years | C96: The Academic years page on a fresh seed | D96: Functional | E96: High | F96: Any | G96: Any time | I96: Signed in as SAO 990001. Fresh seed: one current academic year and no semester. | J96: 1. Open Setup and records > Academic years. 2. Read the card "<year> is the current year" and its three links. 3. Read the Calendar table. 4. Read the Semesters card. 5. Select the first link in the card. | K96: The first card reads "2026-2027 is the current year" with the dates and "At the start of each year": "Publish this year's accreditation requirements" (opens Compliance), "Hand over administrator roles after elections" (opens Administrators), "Open a clearance period for the semester" (opens Clearances). The Calendar table shows the year, its dates and the Current badge. Semesters shows "AY 2026-2027" with "No semesters added." and the button Add semester. With no year the page says "No academic year set" and offers Add academic year (VERIFY on an empty database). | M96: Not run
A97: SAO-096 | B97: Setup and records > Academic years | C97: Add the first semester (the first setup step) | D97: Functional | E97: High | F97: Any | G97: Any time | I97: Signed in as SAO 990001. Fresh seed with no semester yet. | J97: 1. In Semesters select Add semester under AY 2026-2027. 2. Keep 1st Semester selected. 3. Pick Starts on 2026-08-03 and Ends on 2026-12-18 (or any dates inside the year that cover today). 4. Check that the Add semester button was greyed out until both dates were set. 5. Select Add semester. 6. Read the message and the new row. | K97: The message reads "Semester added". The row shows "1st Semester", the dates and the word upcoming, with the buttons Set as active and a trash button. Adding the semester also creates the semester requirements for Compliance > Requirements and Event requirements (VERIFY counts: 11 compliance requirements and 18 event file requirements). Nothing changes for Department Heads yet. | M97: Not run
A98: SAO-097 | B98: Setup and records > Academic years | C98: Semester dates are checked | D98: Validation | E98: High | F98: Any | G98: Any time | I98: Signed in as SAO 990001. A 1st Semester already exists in the year. | J98: 1. Select Add semester for the same year. 2. Choose 1st Semester again, pick any dates and select Add semester. 3. Choose 2nd Semester with dates before the academic year starts and select Add semester. 4. Choose 2nd Semester with dates that overlap the 1st Semester and select Add semester. 5. Choose 2nd Semester with Ends on earlier than Starts on and select Add semester. | K98: Red messages appear under the fields: "This semester already exists for the academic year."; "Semester dates must fall within the academic year."; "Semester dates cannot overlap."; and a message that the end date must be after the start date (VERIFY wording). The Add semester button only shows while the year has fewer than 2 semesters. | M98: Not run
A99: SAO-098 | B99: Setup and records > Academic years | C99: Set a semester as active and see the effect everywhere | D99: Functional | E99: High | F99: Any | G99: Any time | I99: Signed in as SAO 990001. A semester in upcoming status exists. Department Head 940001 and Student 2100142 exist. | J99: 1. Select Set as active on the semester. 2. Read the message and the row. 3. Look at the top bar next to the page title. 4. Sign in as Department Head 940001 and open Organizations. 5. Check the Register an organization form for its required files. 6. Sign in as Student 2100142 and open Events. | K99: The message reads "Academic semester activated". The row shows active and the button Close semester. The top bar shows "AY 2026-2027 · 1st Semester". Department Head 940001 can now register an organization and sees ten required files. Seeded events, tasks and the seeded election belong to no semester, so they disappear from lists once a semester is active (the student sees fewer events). | M99: Not run
A100: SAO-099 | B100: Setup and records > Academic years | C100: A Department Head cannot register before a semester is active | D100: Negative | E100: High | F100: Laptop | G100: Round 2 (after the SAO activates a semester) | I100: Signed in as SAO 990001. Fresh seed with no active semester. Department Head 940001. | J100: 1. Sign in as Department Head 940001 and open Organizations. 2. Try Register an organization and read what the form offers. 3. If the form lets you submit, fill it with ten files and submit. 4. Read the message. 5. Sign in as SAO, set a semester active, then repeat as Department Head. | K100: Before activation the Department Head has no registration requirements and the server refuses with "No registration requirements are open. The SAO must activate a semester first." After the SAO sets a semester as active the form lists the ten files and registration works. | M100: Not run
A101: SAO-100 | B101: Setup and records > Academic years | C101: Close a semester and activate the next one | D101: Functional | E101: Medium | F101: Any | G101: Round 2 (after the SAO activates a semester) | I101: Signed in as SAO 990001. An active 1st Semester and an upcoming 2nd Semester exist in the same year. | J101: 1. Select Close semester on the active semester. 2. Read the message and the row. 3. Check the completed semester for a Set as active button. 4. Select Set as active on the 2nd Semester. 5. Read the rows. | K101: Closing shows "Academic semester completed" and the row reads completed with no Set as active button (a completed semester cannot be reopened: "A completed semester cannot be reopened."). Activating the 2nd Semester makes it active and completes any other active semester. Activating a semester in a new year while the current year still has an unfinished semester is refused with "Complete both semesters in the current academic year before starting a new year." | M101: Not run
A102: SAO-101 | B102: Setup and records > Academic years | C102: Delete a semester | D102: Negative | E102: Medium | F102: Any | G102: Round 2 (after the SAO activates a semester) | I102: Signed in as SAO 990001. An upcoming 2nd Semester with nothing attached, an active semester, and a semester that has events exist (if you cannot set this up, test only the first two). | J102: 1. Select the trash button named "Delete 2nd semester of AY 2026-2027", read the box and select Cancel. 2. Select the trash button again and select Delete semester. 3. Read the message. 4. Look for a trash button on the active semester. 5. Select the trash button on the semester that has events and select Delete semester. | K102: The box says it cannot be undone and that a semester with events, tasks or requirements attached cannot be deleted. A clean semester is removed with "Semester removed". The active semester has no trash button. A semester with attached data is refused with "This semester cannot be deleted because of: events." followed by a bullet list of reasons. | M102: Not run
A103: SAO-102 | B103: Setup and records > Academic years | C103: Add an academic year | D103: Functional | E103: High | F103: Any | G103: Any time | I103: Signed in as SAO 990001. | J103: 1. Select Add academic year. 2. Pick Starts on 2027-08-02 and check that Label fills in "2027-2028". 3. Pick Ends on 2028-05-26. 4. Check that the Add academic year button was greyed out until all three fields were filled. 5. Select Add academic year. 6. Read the message and the Calendar table. | K103: The message reads "2027-2028 added to the calendar" and the year appears in the Calendar table as Not current. (Only the very first year ever added becomes current: then the message reads "<label> is now the current academic year".) The Semesters card gets an "AY 2027-2028" block. | M103: Not run
A104: SAO-103 | B104: Setup and records > Academic years | C104: Academic year form refuses bad labels and dates | D104: Validation | E104: High | F104: Any | G104: Any time | I104: Signed in as SAO 990001. | J104: 1. Open Add academic year and type Label 27-28 with valid dates, then select Add academic year. 2. Change Label to 2027-2029 and select Add academic year. 3. Use a Label not yet used but dates that overlap the current year and select Add academic year. 4. Set Ends on earlier than Starts on and select Add academic year. 5. Use the label of an existing year and select Add academic year. | K104: Red messages appear under the fields: "Use the form 2026-2027."; "Use two consecutive years, like 2026-2027."; "These dates overlap 2026-2027." (or the year name that overlaps); a message that the end date must be after the start date; and a message that the label has already been used (VERIFY wording). Nothing is added. | M104: Not run
A105: SAO-104 | B105: Setup and records > Academic years | C105: Edit an academic year; rename and shrink are limited | D105: Validation | E105: Medium | F105: Any | G105: Any time | I105: Signed in as SAO 990001. The current year has a semester and has requirements. | J105: 1. Select Edit on the current year. 2. Change Ends on so that it is earlier than the end of its semester and select Save changes. 3. Read the message. 4. Change the Label and select Save changes. 5. Read the message. | K105: The dialog is titled "Edit 2026-2027". Shrinking the dates is refused with "Academic year dates must still contain its semesters." A new label is refused with "<label> already labels requirements or clearance periods, so its name stays." Valid date changes save with "<label> updated". | M105: Not run
A106: SAO-105 | B106: Setup and records > Academic years | C106: Make a year current, remove a year and close a year | D106: Functional | E106: Medium | F106: Any | G106: Any time | I106: Signed in as SAO 990001. A second academic year (2027-2028) exists. The current year has both semesters completed for the Close year step. | J106: 1. Select Make current on the second year. 2. Read the box titled "Make this the current year" and select Make current. 3. Read the message. If a semester is active, read the red message instead. 4. Select the trash button named "Remove 2027-2028" (only non-current years have one) and select Remove year. 5. On a current year whose two semesters are completed select Close year and confirm. | K106: The box says accreditation will count this year's requirements. The message reads "<label> is now the current academic year", or while a semester is active it is refused with "Activate a semester in this year to change the active academic period." A year in use is refused with "<label> already has accreditation requirements or clearance periods, so it stays on the calendar." An unused year shows "<label> removed". Close year shows "AY <label> completed" and the year then reads Completed and cannot be reopened. | M106: Not run
A107: SAO-106 | B107: Setup and records > Audit trail | C107: The audit trail lists activity and each record has details | D107: Functional | E107: High | F107: Laptop | G107: Any time | I107: Signed in as SAO 990001. | J107: 1. Open Setup and records > Audit trail. 2. Read the table columns and the entry count. 3. Open the Audit actions menu of a row and choose View details. 4. Read the dialog. 5. Select the close button named "Close audit details". | K107: Columns are Time, Actor, Role, Organization, Module, Action, Affected record, Record ID, Details. The count reads "N entries" and the newest entry is first. The dialog reads "Audit record LOG-<id>" with Actor, Actor role / position, Actor academic profile, Affected record, Record type, Record ID, IP address, Timestamp, and a Before / after changes table (Field, Before, After) or the text "No field-level change payload was recorded for this action." | M107: Not run
... A110: SAO-109 | B110: Setup and records > Audit trail | C110: Export the audit trail to a CSV file | D110: Functional | E110: Medium | F110: Laptop | G110: Any time | I110: Signed in as SAO 990001. | J110: 1. Choose a Module so that the list has some entries. 2. Select Export CSV. 3. Read the message. 4. Open the downloaded file audit-log-<number>.csv. 5. Choose filters that match nothing and look at the Export CSV button. | K110: The button shows "Exporting..." and then a message "Audit log exported." with "Every entry matching your filters, not just this page." The file holds every matching entry. With zero matching entries the button is greyed out. | M110: Not run
...

Sheet Department Head
A1: ID | B1: Module | C1: Test case | D1: Type | E1: Priority | F1: Device | G1: Round | H1: Depends on | I1: Preconditions | J1: Steps | K1: Expected result | L1: Author note (unconfirmed) | M1: Status | N1: Severity | O1: Tester | P1: Date tested | Q1: Device and browser used | R1: Actual result / notes | S1: Bug screenshot link
A2: DH-001 | B2: Sign in | C2: Department Head signs in and lands on the Department Head dashboard | D2: Functional | E2: High | F2: Any | G2: Any time | I2: Account 940001 exists. The password is given to you separately. | J2: 1. Open the HIUSA address in a browser. 2. Type 940001 in School ID / ID Number. 3. Type the password you were given. 4. Select Sign in. | K2: You land on the Department Head Dashboard (the address ends with /dashboard/department-head). The top bar shows your name, your college and the label Department Head. The menu is the Department Head menu. | M2: Not run
A3: DH-002 | B3: Sign in | C3: Wrong password is refused with a clear message | D3: Negative | E3: High | F3: Any | G3: Any time | I3: Account 940001 exists. Use a different account than the one your teammates are using, because five wrong tries lock an account for 15 minutes. | J3: 1. Open the HIUSA address. 2. Type 940001 in School ID / ID Number. 3. Type a wrong password. 4. Select Sign in. | K3: You stay on the Sign in page. A message says: That school ID and password did not match. Check both and try again, or reset your password. No dashboard opens. | M3: Not run
A4: DH-003 | B4: Menu | C4: Sidebar shows exactly the Department Head menu | D4: Access | E4: High | F4: Any | G4: Any time | I4: Sign in as Department Head 940001 (College of Computer Studies, home of PSITS-CCS). The password is given to you separately. | J4: 1. Look at the left menu after sign in. 2. Read the top rows in order. 3. Find the heading College view (read only) and read what is under it. 4. Select Finance and read its sub items. 5. Look at the bottom of the menu. | K4: The menu reads: Dashboard, Approvals, Organizations. Under the heading College view (read only): Finance (Budgets, Ledger, Financial reports, Forecast), Calendar, Election results, Announcements. At the bottom: Profile and Study objectives. There is NO Members, Events and tasks, Voting, Store, Updates, Records or My activity group. Selecting Finance opens Budgets. | M4: Not run
A5: DH-004 | B5: Menu | C5: Phone: the menu opens from Open menu and every Department Head page can be reached | D5: Usability | E5: Medium | F5: Phone | G5: Any time | I5: Sign in as Department Head 940001 (College of Computer Studies, home of PSITS-CCS). The password is given to you separately. Use a phone or a browser window narrower than 1024 pixels. | J5: 1. Look at the top left of the screen. 2. Tap Open menu. 3. Tap Organizations. 4. Tap Open menu again and tap Approvals. 5. Tap Open menu again and tap Close menu. | K5: The menu slides in as a drawer. Each tap opens the right page and the drawer closes. Close menu hides the drawer. Nothing is cut off at the sides and no page scrolls sideways. | M5: Not run
A6: DH-005 | B6: Account menu | C6: Top bar shows who you are and the account menu has only your profile and Logout | D6: Usability | E6: Medium | F6: Any | G6: Any time | I6: Sign in as Department Head 940001 (College of Computer Studies, home of PSITS-CCS). The password is given to you separately. | J6: 1. Look at the top right of the screen. 2. Read your name, your college name and the label Department Head. 3. Select the account button (its name starts with Account menu for). 4. Read the Profiles section. 5. Look at the buttons under it. | K6: Your name, college and Department Head are shown. The Profiles section lists one profile with the word Current and says: This is your only active profile. Other profiles appear here when an organization adds you. The buttons are View Profile and Logout. | L6: VERIFY: the exact college text shown in the top bar (it comes from the college home organization). | M6: Not run
A7: DH-006 | B7: Account menu | C7: Logout asks first, then returns to Sign in | D7: Functional | E7: Medium | F7: Any | G7: Any time | I7: Sign in as Department Head 940001 (College of Computer Studies, home of PSITS-CCS). The password is given to you separately. | J7: 1. Select the account button in the top bar. 2. Select Logout. 3. Read the question that appears. 4. Confirm the logout. 5. Press the browser Back button. | K7: A confirmation appears before you are signed out. After you confirm, the Sign in page shows. Back should not show private pages again; you are asked to sign in. | L7: VERIFY: the exact words on the confirmation and what Back shows. | M7: Not run
A8: DH-007 | B8: Dashboard | C8: Dashboard shows the college, the approvals and the oversight snapshot | D8: Functional | E8: High | F8: Any | G8: Any time | I8: Sign in as Department Head 940001 (College of Computer Studies, home of PSITS-CCS). The password is given to you separately. | J8: 1. Select Dashboard in the menu. 2. Read the greeting at the top. 3. Find the box titled College of Computer Studies organizations. 4. Find the box titled Oversight snapshot. 5. Scroll down to Upcoming Events, Pending Approvals by Type and Recent Announcements. | K8: The page loads without an error. The college box says: Every student organization you oversee, by registration status. The Oversight snapshot has four tiles: Active Elections, Closed Elections, Upcoming Events, Pending Approvals. The lower boxes are Upcoming Events, Pending Approvals by Type and Recent Announcements. A box with nothing in it shows a short plain message, not a blank gap. | M8: Not run
A9: DH-008 | B9: Dashboard | C9: Organization status tiles show counts and open the matching list | D9: Functional | E9: High | F9: Any | G9: Any time | I9: Sign in as Department Head 940001 (College of Computer Studies, home of PSITS-CCS). The password is given to you separately. PSITS-CCS is Active. Register one more organization (see the Organizations cases) so there is also a Pending review row. | J9: 1. Open Dashboard. 2. In the college box read the four tiles: Returned, Pending review, Active, Archived. 3. Select the Pending review tile. 4. Look at the address and the tab that is selected. 5. Go back to Dashboard and select Manage organizations. | K9: Each tile shows a number that matches the rows in Organizations. The Pending review tile opens Organizations with the Pending review tab selected (the address ends with ?status=pending). Manage organizations opens Organizations with All selected. A Returned tile with a number above 0 is red and says Action needed. | M9: Not run
A10: DH-009 | B10: Dashboard | C10: Approvals banner counts the items waiting for the head and opens Approvals | D10: Functional | E10: High | F10: Any | G10: Any time | I10: A semester is active. Admin 900001 (PSITS-CCS) has proposed an event with dates inside the semester, so it waits for the Department Head. | J10: 1. Open Dashboard. 2. Find the yellow banner that says N item awaiting your approval. 3. Compare N with the Pending Approvals tile in Oversight snapshot. 4. Select the banner. | K10: The banner reads, for example, 1 item awaiting your approval (or items for more than one), with the line: Events, elections, and first-stage financial reports need your sign-off. The number matches the Pending Approvals tile. Selecting the banner opens Approvals. When nothing is pending the banner is not shown. | M10: Not run
A11: DH-010 | B11: Dashboard | C11: Election card and Upcoming Events box, including the empty messages | D11: Functional | E11: Medium | F11: Any | G11: Any time | I11: Sign in as Department Head 940001 (College of Computer Studies, home of PSITS-CCS). The password is given to you separately. | J11: 1. Open Dashboard. 2. Find the election card. It says either Active Election or No Active Election. 3. If an election is active, select View Results. 4. Go back to Dashboard and read the Upcoming Events box. 5. Select View all in the Upcoming Events box. | K11: With no running election the card says No Active Election and: No elections are currently running. With one running it shows the title, dates, a LIVE tag, View Details and View Results (View Results opens Election results). Upcoming Events lists up to four events with date, place and status, or says No upcoming events. View all opens the events list of your college. | M11: Not run
A12: DH-011 | B12: Dashboard | C12: Pending Approvals by Type and Recent Announcements boxes | D12: Functional | E12: Medium | F12: Any | G12: Any time | I12: A semester is active. Admin 900001 (PSITS-CCS) has proposed an event with dates inside the semester, so it waits for the Department Head. | J12: 1. Open Dashboard. 2. Find the box Pending Approvals by Type. 3. Select one request listed in it. 4. Go back to Dashboard and find the box Recent Announcements. 5. Select View all in that box. | K12: Pending Approvals by Type lists up to three waiting requests and a bar per type with a count and a percent. Selecting a request opens Approvals. With nothing waiting it says: Nothing awaiting your review. Recent Announcements shows up to three published announcements, or No announcements yet. View all opens Announcements. | M12: Not run
A13: DH-012 | B13: Dashboard | C13: Getting started card: registration is blocked until the SAO opens a semester | D13: Functional | E13: Medium | F13: Any | G13: Any time | I13: A fresh seed where the SAO has NOT activated a semester yet. Sign in as Department Head 940001 (College of Computer Studies, home of PSITS-CCS). The password is given to you separately. | J13: 1. Open Dashboard. 2. Find the card Getting started. 3. Read the step Register your first student organization. 4. Look for a button on that step. 5. Read the other two steps: Follow your registration and Review approvals. | K13: The register step shows the note Waiting for the SAO to open the semester and has NO button. The other steps are listed: Follow your registration and Review approvals (its button is Open approvals). | L13: VERIFY: the card only shows while the steps are not all done and it has not been hidden. | M13: Not run
A14: DH-013 | B14: Dashboard | C14: A returned registration leads the Needs attention list | D14: Functional | E14: High | F14: Any | G14: Any time | I14: The SAO has activated a semester first (SAO: Setup and records > Academic years > Add semester, then Set as active). A fresh seed has no semester. The SAO has returned a registration with remarks (see the returned registration case). | J14: 1. Open Dashboard. 2. Find the box Needs attention. 3. Find the row Registration returned: and the organization name. 4. Read the detail line under it. 5. Select the row, or select Edit and resubmit in the Getting started card. | K14: Registration rows come first in the list. The row shows the SAO remarks (cut to 160 characters) or, when there are none: The SAO returned this registration. Edit it and submit it again. Selecting it opens Organizations on the Returned tab. | M14: Not run
A15: DH-014 | B15: Dashboard | C15: Phone: the dashboard fits the screen | D15: Usability | E15: Medium | F15: Phone | G15: Any time | I15: Sign in as Department Head 940001 (College of Computer Studies, home of PSITS-CCS). The password is given to you separately. Use a phone. | J15: 1. Open Dashboard on a phone. 2. Scroll from top to bottom. 3. Tap the Returned, Pending review, Active and Archived tiles one by one. 4. Tap Open menu and then Approvals. | K15: Tiles stack in one or two columns. Text is readable and nothing is cut off. Tiles are big enough to tap. The page does not scroll sideways. | M15: Not run
A16: DH-015 | B16: Organizations | C16: Organizations page layout and the status tabs | D16: Functional | E16: High | F16: Any | G16: Any time | I16: Sign in as Department Head 940001 (College of Computer Studies, home of PSITS-CCS). The password is given to you separately. | J16: 1. Select Organizations in the menu. 2. Read the line under the page title. 3. Look at the card Your college. 4. Look at the tabs above the table. 5. Read the table column names. | K16: The line says: Student organizations registered under your college. Register new ones and follow their SAO review. The card shows the college name and Department Head: your name. The tabs read All (n), Returned (n), Pending review (n), Active (n), Archived (n). Columns: Organization, Status, Admins, SBO Officers, Students, Submitted. The button Register an organization is at the top right. | M16: Not run
A17: DH-016 | B17: Organizations | C17: Status tabs filter the list and the address remembers the tab | D17: Functional | E17: Medium | F17: Any | G17: Any time | I17: Sign in as Department Head 940001 (College of Computer Studies, home of PSITS-CCS). The password is given to you separately. At least two organizations with different statuses. | J17: 1. Open Organizations. 2. Select the Active tab. 3. Look at the address bar. 4. Select the Pending review tab. 5. Select All. 6. Refresh the page while on Pending review. | K17: Each tab shows only organizations with that status and the number in the tab matches the rows. The address changes to ?status=active or ?status=pending and All removes it. After a refresh the same tab stays selected. | M17: Not run
A18: DH-017 | B18: Organizations | C18: Empty tab shows a clear message | D18: Usability | E18: Medium | F18: Any | G18: Any time | I18: Sign in as Department Head 940001 (College of Computer Studies, home of PSITS-CCS). The password is given to you separately. A tab that has zero organizations, for example Archived (0). | J18: 1. Open Organizations. 2. Select a tab whose count is 0, for example Archived. 3. Read the message in the table area. | K18: The table shows: No archived organizations (the status name matches the tab), with the text Choose another status to see the rest of your college. No error and no blank screen. | M18: Not run
A19: DH-018 | B19: Organizations | C19: View checklist of an active organization | D19: Functional | E19: Medium | F19: Any | G19: Any time | I19: Sign in as Department Head 940001 (College of Computer Studies, home of PSITS-CCS). The password is given to you separately. PSITS-CCS is Active on the fresh seed. | J19: 1. Open Organizations. 2. Find the row PSITS-CCS. 3. Select View checklist. 4. Read the panel that slides in: status, progress steps, Leadership, the Admins, SBO Officers and Students counts. 5. Read the Requirement checklist. 6. Select Close. | K19: A side panel titled with the organization name opens. It shows the Active status, the registration progress steps, the Leadership names (or: No Admin or SBO Officer is assigned yet.), three counts, and the Requirement checklist (or: No registration documents are on file.). Close shuts the panel and the address loses ?record=. | M19: Not run
A20: DH-019 | B20: Organizations | C20: Register form opens with one file box for each requirement | D20: Functional | E20: High | F20: Any | G20: Any time | I20: The SAO has activated a semester first (SAO: Setup and records > Academic years > Add semester, then Set as active). A fresh seed has no semester. Sign in as Department Head 940001 (College of Computer Studies, home of PSITS-CCS). The password is given to you separately. | J20: 1. Open Organizations. 2. Select Register an organization. 3. Read the form title and the text under it. 4. Scroll to Registration requirements and count the file boxes. 5. Read the line under Registration requirements. | K20: A form titled Register an organization opens. It says: The SAO reviews every registration. Attach all required documents as PDF files. There is one file box per requirement (ten on the fresh seed), each marked required. The line reads Academic year 2026-2027, semester 1 (the real year and number) and PDF only, up to 10 MB each. | M20: Not run
A21: DH-020 | B21: Organizations | C21: No active semester: the register form explains why it cannot be sent | D21: Negative | E21: High | F21: Any | G21: Any time | I21: A fresh seed where the SAO has NOT activated a semester yet. Sign in as Department Head 940001 (College of Computer Studies, home of PSITS-CCS). The password is given to you separately. | J21: 1. Open Organizations. 2. Select Register an organization. 3. Read the yellow message. 4. Look for a Submit for review button. 5. Select Close. | K21: The yellow message says: No registration requirements are open. The SAO must activate a semester first. There are no fields and NO Submit for review button. Only Close is offered. | M21: Not run
A22: DH-021 | B22: Organizations | C22: Register an organization with all documents | D22: Functional | E22: High | F22: Any | G22: Any time | I22: The SAO has activated a semester first (SAO: Setup and records > Academic years > Add semester, then Set as active). A fresh seed has no semester. Sign in as Department Head 940001 (College of Computer Studies, home of PSITS-CCS). The password is given to you separately. Have ten small PDF files ready on the device (any PDF under 10 MB). Use a new name that no organization has. | J22: 1. Open Organizations and select Register an organization. 2. Type a new Organization name. 3. Type a new Acronym. 4. Optional: fill Description and Color (for example #0B8ED0). 5. Choose one PDF in every file box. 6. Select Submit for review. | K22: The form closes. A message says: Organization submitted to the SAO for review. The new row appears with the status Pending review and the line Pending review: waiting for SAO review. The Pending review tab count goes up by one. The SAO gets a notification New organization registration. | M22: Not run
A23: DH-022 | B23: Organizations | C23: Register form: blank name, acronym and files are refused | D23: Validation | E23: High | F23: Any | G23: Any time | I23: The SAO has activated a semester first (SAO: Setup and records > Academic years > Add semester, then Set as active). A fresh seed has no semester. Sign in as Department Head 940001 (College of Computer Studies, home of PSITS-CCS). The password is given to you separately. | J23: 1. Open Organizations and select Register an organization. 2. Leave everything empty. 3. Select Submit for review. 4. Read each red message. 5. Note which field has the cursor. | K23: Nothing is sent. Messages: Enter the organization name. Enter the acronym. And under every file box: Attach a PDF for this requirement. The cursor moves to the first field with a problem. | M23: Not run
A24: DH-023 | B24: Organizations | C24: Register form: one missing document is named | D24: Validation | E24: Medium | F24: Any | G24: Any time | I24: The SAO has activated a semester first (SAO: Setup and records > Academic years > Add semester, then Set as active). A fresh seed has no semester. Sign in as Department Head 940001 (College of Computer Studies, home of PSITS-CCS). The password is given to you separately. | J24: 1. Open Organizations and select Register an organization. 2. Type a new name and a new acronym. 3. Choose a PDF in all file boxes except the last one. 4. Select Submit for review. 5. Read the messages. | K24: Only the last file box shows Attach a PDF for this requirement. The nine boxes with a file show no error. The form stays open and your typed text is kept. | M24: Not run
A25: DH-024 | B25: Organizations | C25: Register form: only PDF files are accepted | D25: Validation | E25: High | F25: Any | G25: Any time | I25: The SAO has activated a semester first (SAO: Setup and records > Academic years > Add semester, then Set as active). A fresh seed has no semester. Sign in as Department Head 940001 (College of Computer Studies, home of PSITS-CCS). The password is given to you separately. Have a picture or a Word file ready. | J25: 1. Open Organizations and select Register an organization. 2. In the first file box choose a picture (.jpg) or a Word file. 3. Read the message under that box. 4. Choose a real PDF in the same box. | K25: The message under the box says: Only PDF files are accepted. The wrong file is not kept. After you choose a PDF the message goes away and the file name shows as Selected: with its size. | M25: Not run
... A27: DH-026 | B27: Organizations | C27: Register form: a wrong color code is refused | D27: Validation | E27: Low | F27: Any | G27: Any time | I27: The SAO has activated a semester first (SAO: Setup and records > Academic years > Add semester, then Set as active). A fresh seed has no semester. Sign in as Department Head 940001 (College of Computer Studies, home of PSITS-CCS). The password is given to you separately. | J27: 1. Open Organizations and select Register an organization. 2. Fill name, acronym and all ten PDFs. 3. In Color type blue. 4. Select Submit for review. 5. Change Color to #0B8ED0 and select Submit for review again. | K27: The first try shows: Use a color like #0B8ED0. and nothing is sent. With #0B8ED0 (or an empty Color) it is accepted. The small colored square next to Color follows what you type when the code is valid. | M27: Not run
A28: DH-027 | B28: Organizations | C28: Register form: a name or acronym that already exists is refused | D28: Validation | E28: Medium | F28: Any | G28: Any time | I28: The SAO has activated a semester first (SAO: Setup and records > Academic years > Add semester, then Set as active). A fresh seed has no semester. Sign in as Department Head 940001 (College of Computer Studies, home of PSITS-CCS). The password is given to you separately. PSITS-CCS already exists. | J28: 1. Open Organizations and select Register an organization. 2. Type the name of an existing organization (copy it from the list). 3. Type a new acronym and choose all ten PDFs. 4. Select Submit for review. 5. Change the name to a new one and the acronym to PSITS-CCS. 6. Select Submit for review. | K28: The form stays open and nothing is saved. Under Organization name you see a message that the name is already taken. Under Acronym you see a message that the acronym is already taken. | L28: VERIFY: the exact server wording (expected: The name has already been taken. and The acronym has already been taken.). A very similar name may instead say: An organization with a similar name already exists. | M28: Not run
A29: DH-028 | B29: Organizations | C29: Cancel the register form: nothing is saved | D29: Functional | E29: Low | F29: Any | G29: Any time | I29: The SAO has activated a semester first (SAO: Setup and records > Academic years > Add semester, then Set as active). A fresh seed has no semester. Sign in as Department Head 940001 (College of Computer Studies, home of PSITS-CCS). The password is given to you separately. | J29: 1. Open Organizations and select Register an organization. 2. Type a name and choose one PDF. 3. Click on the dark area outside the form. 4. Select Cancel. 5. Look at the list. | K29: Clicking outside the form does NOT close it. Cancel closes it. No new row is in the list and no notice is sent to the SAO. | M29: Not run
A30: DH-029 | B30: Organizations | C30: SAO returns a registration: the head sees the remarks | D30: Functional | E30: High | F30: Any | G30: Any time | I30: The SAO has activated a semester first (SAO: Setup and records > Academic years > Add semester, then Set as active). A fresh seed has no semester. Sign in as Department Head 940001 (College of Computer Studies, home of PSITS-CCS). The password is given to you separately. The head has a Pending review registration. The SAO (Organizations > Registrations and organizations) returns it with the remarks: Replace the constitution with the signed copy. | J30: 1. Open the bell in the top bar. 2. Find the notice Organization registration returned. 3. Select it and read it. 4. Open Organizations and select the Returned tab. 5. Read the row. | K30: The notice says the organization was returned and repeats the remarks. The row has the red status Returned, the line Returned: edit and resubmit and a red box SAO remarks with the SAO text. The row has three buttons: View checklist, Edit and resubmit, Withdraw. | M30: Not run
A31: DH-030 | B31: Organizations | C31: Edit and resubmit a returned registration | D31: Functional | E31: High | F31: Any | G31: Any time | I31: The SAO has activated a semester first (SAO: Setup and records > Academic years > Add semester, then Set as active). A fresh seed has no semester. Sign in as Department Head 940001 (College of Computer Studies, home of PSITS-CCS). The password is given to you separately. The head has a Returned registration. | J31: 1. Open Organizations and select the Returned tab. 2. Select Edit and resubmit on the returned row. 3. Read the form title and the red SAO remarks box. 4. Change the Description. 5. Select Resubmit to SAO. | K31: The form title is Edit and resubmit and the organization name. It says: Change the details and replace only the documents the SAO returned. Resubmitting sends it back to the SAO for review. The SAO remarks show at the top. After Resubmit to SAO a message says: Registration resubmitted to the SAO. The row now shows Pending review: waiting for SAO review and the SAO gets a notice Organization registration resubmitted. | M31: Not run
A32: DH-031 | B32: Organizations | C32: Resubmit with one replaced document | D32: Functional | E32: Medium | F32: Any | G32: Any time | I32: The SAO has activated a semester first (SAO: Setup and records > Academic years > Add semester, then Set as active). A fresh seed has no semester. Sign in as Department Head 940001 (College of Computer Studies, home of PSITS-CCS). The password is given to you separately. The head has a Returned registration. | J32: 1. Open Organizations, Returned tab, then Edit and resubmit. 2. Find the file box you want to change. Read Current file: under it. 3. Choose a different PDF in that one box only. 4. Leave all other boxes empty. 5. Select Resubmit to SAO. 6. Open View checklist on the row. | K32: The other documents are not required again (the boxes are not marked required). The row goes back to Pending review. In View checklist the replaced requirement shows the new file name and the status Submitted. The unchanged documents keep their old file names. | M32: Not run
A33: DH-032 | B33: Organizations | C33: Resubmit form: a blank name or a wrong file is refused | D33: Validation | E33: Medium | F33: Any | G33: Any time | I33: The SAO has activated a semester first (SAO: Setup and records > Academic years > Add semester, then Set as active). A fresh seed has no semester. Sign in as Department Head 940001 (College of Computer Studies, home of PSITS-CCS). The password is given to you separately. The head has a Returned registration. | J33: 1. Open Organizations, Returned tab, then Edit and resubmit. 2. Clear the Organization name. 3. Choose a picture file in one file box. 4. Select Resubmit to SAO. 5. Read the messages. | K33: Messages: Enter the organization name. and Only PDF files are accepted. Nothing is sent and the row stays Returned. | M33: Not run
A34: DH-033 | B34: Organizations | C34: Buttons shown on each row depend on the status | D34: Access | E34: High | F34: Any | G34: Any time | I34: Sign in as Department Head 940001 (College of Computer Studies, home of PSITS-CCS). The password is given to you separately. One Pending review row and PSITS-CCS (Active). | J34: 1. Open Organizations. 2. Look at the buttons on the Pending review row. 3. Look at the buttons on the Active row PSITS-CCS. 4. Look at the buttons on a Returned row if you have one. | K34: Pending review row: View checklist and Withdraw. There is NO Edit and resubmit. Active row: View checklist only (no Withdraw, no Edit). Returned row: View checklist, Edit and resubmit and Withdraw. The head cannot change an active organization. | M34: Not run
A35: DH-034 | B35: Organizations | C35: Withdraw a pending registration | D35: Functional | E35: High | F35: Any | G35: Any time | I35: The SAO has activated a semester first (SAO: Setup and records > Academic years > Add semester, then Set as active). A fresh seed has no semester. Sign in as Department Head 940001 (College of Computer Studies, home of PSITS-CCS). The password is given to you separately. The head has a Pending review registration that nobody uses yet. | J35: 1. Open Organizations and select Withdraw on the Pending review row. 2. Read the question and the warning. 3. Select Keep registration. 4. Select Withdraw again and then Withdraw registration. 5. Look at the list. | K35: The question is Withdraw this registration? with the organization name and the warning: The SAO is told it was withdrawn and its documents are removed. This cannot be undone. Keep registration closes it and the row stays. Withdraw registration removes the row and shows: <name> withdrawn. The SAO gets a notice Organization registration withdrawn. | M35: Not run
A36: DH-035 | B36: Organizations | C36: SAO approves: the head sees Active and the next step | D36: Functional | E36: High | F36: Any | G36: Any time | I36: The SAO has activated a semester first (SAO: Setup and records > Academic years > Add semester, then Set as active). A fresh seed has no semester. Sign in as Department Head 940001 (College of Computer Studies, home of PSITS-CCS). The password is given to you separately. The head has a Pending review registration. The SAO approves it and has NOT yet created its administrator. | J36: 1. Open the bell and read the notice Organization registration approved. 2. Open Organizations and select the Active tab. 3. Find the new organization. 4. Read the status line under its name. 5. Open Dashboard and look at Needs attention. | K36: The notice says the organization was approved and is now active. The row shows Active and the line Approved: waiting for an administrator. Admins shows 0. Dashboard Needs attention shows Organization approved: waiting for an administrator. After the SAO creates the administrator, the row reads Active: administrator can sign in and Admins shows 1. | M36: Not run
A37: DH-036 | B37: Organizations | C37: Archived organization is read only | D37: Access | E37: Medium | F37: Any | G37: Any time | I37: Sign in as Department Head 940001 (College of Computer Studies, home of PSITS-CCS). The password is given to you separately. The SAO has archived an organization of this college (Organizations > open it > Archive). | J37: 1. Open Organizations and select the Archived tab. 2. Find the archived row. 3. Read the text under its name. 4. Look at the buttons on the row. 5. Select View checklist. | K37: The row looks grey and says Archived by the SAO. Read only. The only button is View checklist. The side panel also says Archived by the SAO. Read only. The head cannot restore, edit or withdraw it. | M37: Not run
A38: DH-037 | B38: Organizations | C38: Head cannot create an administrator or assign roles | D38: Access | E38: High | F38: Any | G38: Any time | I38: Sign in as Department Head 940001 (College of Computer Studies, home of PSITS-CCS). The password is given to you separately. An Active organization with 0 Admins (just approved by the SAO). | J38: 1. Open Organizations. 2. Select View checklist on the organization with 0 Admins. 3. Read the next step box. 4. Look for any button that creates an administrator or changes a role. | K38: The box says Approved: waiting for an administrator (and that the SAO assigns it). There is NO Create administrator, Add user or role button anywhere on the page. Only the SAO can provision an administrator. | M38: Not run
A39: DH-038 | B39: Organizations | C39: Another college head sees only their own college | D39: Access | E39: High | F39: Any | G39: Any time | I39: Two registrations exist: one by the CCS head (940001) and PSITS-CCS. Sign in as 940002 (College of Business). | J39: 1. Sign in as 940002. 2. Open Organizations. 3. Read the college name in the Your college card. 4. Look for PSITS-CCS and for the organization the CCS head registered. 5. Copy the address of the CCS head Organizations page with ?record= and an id of a CCS organization, and open it in 940002. | K39: Only organizations of the Business college show (for example JPIA-CBE). PSITS-CCS and the CCS registration are not listed. Opening a CCS organization by address shows a red message: That organization is not in your college, so there is nothing to open. | L39: VERIFY: the exact Business college name shown. | M39: Not run
A40: DH-039 | B40: Organizations | C40: Phone: list, register form and panels are usable | D40: Usability | E40: Medium | F40: Phone | G40: Any time | I40: The SAO has activated a semester first (SAO: Setup and records > Academic years > Add semester, then Set as active). A fresh seed has no semester. Sign in as Department Head 940001 (College of Computer Studies, home of PSITS-CCS). The password is given to you separately. Use a phone. | J40: 1. Open Organizations on the phone. 2. Scroll the list. Rows appear as cards. 3. Tap Register an organization and scroll the whole form. 4. Choose a PDF in one box. 5. Tap Cancel. 6. Tap View checklist on PSITS-CCS. | K40: Cards show name, status and counts. The form scrolls inside its window, the buttons Cancel and Submit for review stay reachable, and file boxes work. The side panel fits the screen. Nothing is cut off and the page does not scroll sideways. | M40: Not run
A41: DH-040 | B41: Approvals | C41: Approvals page layout and filters | D41: Functional | E41: High | F41: Any | G41: Any time | I41: A semester is active. Admin 900001 (PSITS-CCS) has proposed an event with dates inside the semester, so it waits for the Department Head. | J41: 1. Select Approvals in the menu. 2. Read the two buttons Pending (n) and All History. 3. Read the filter row: Search requests, Request type, Organization, Requested from, Requested to, Sort order. 4. Read the line under the filters. 5. Look at one request row. | K41: Pending (n) is selected. The count line reads N matching requests and M awaiting action. Buttons Reset and Export CSV are there. Each row shows the title, a type tag (Event, Budget, Election, Financial Report), the organization name, a status badge, who requested it and when, a small progress stepper, a line saying whose turn it is (for the head it should read as waiting for the Department Head), and the button Review. | L41: VERIFY: the exact stage wording. | M41: Not run
A42: DH-041 | B42: Approvals | C42: Approve an event proposal | D42: Functional | E42: High | F42: Any | G42: Any time | I42: A semester is active. Admin 900001 (PSITS-CCS) has proposed an event with dates inside the semester, so it waits for the Department Head. Sign in as Department Head 940001 (College of Computer Studies, home of PSITS-CCS). The password is given to you separately. | J42: 1. Open Approvals. 2. Select Review on the event row. 3. Read the panel: progress steps, next step, details and History. 4. Select Approve in the panel. 5. In the window Approve request, type an optional remark and select Approve. 6. Look at the panel again. | K42: A window titled Approve with the event title opens, with Remarks (optional). After Approve a message says: Request approved. The panel now reads Approved (or a longer sentence about the SAO, see the next case), the buttons Approve and Reject are gone, and a link Open event shows. History shows Approved by with your name. The Admin gets a notice about the decision. | M42: Not run
A43: DH-042 | B43: Approvals | C43: Event that needs SAO files: what the head sees after approving | D43: Access | E43: High | F43: Any | G43: Round 2 (after the SAO activates a semester) | I43: A semester is active. Admin 900001 (PSITS-CCS) has proposed an event with dates inside the semester, so it waits for the Department Head. The event needs SAO files (an on-campus or other venue type that the SAO requires, with an active semester). | J43: 1. Open Approvals and select Review on the event. 2. Select Approve and confirm. 3. Read the sentence at the top of the panel. 4. Open All History and find the same request. 5. Look for any Approve or Reject button. | K43: The panel says: Approved. Waiting for the organization to submit the SAO event files (before files are uploaded) or Approved. Now with the SAO for requirements review (after). The head has no button to do the SAO step. The head approves first, then the SAO decides. | L43: VERIFY: whether your event needs SAO files depends on its venue type. | M43: Not run
A44: DH-043 | B44: Approvals | C44: Rejecting needs a reason | D44: Validation | E44: High | F44: Any | G44: Any time | I44: A semester is active. Admin 900001 (PSITS-CCS) has proposed an event with dates inside the semester, so it waits for the Department Head. Sign in as Department Head 940001 (College of Computer Studies, home of PSITS-CCS). The password is given to you separately. | J44: 1. Open Approvals and select Review on a pending request. 2. Select Reject. 3. Look at the Reject button in the window while Remarks is empty. 4. Type Budget not yet finalized. in Remarks. 5. Select Reject. 6. Read the panel. | K44: The window title starts with Reject and the label says Remarks (required). With Remarks empty the Reject button is greyed out and cannot be selected. After typing, Reject works. A message says: Request rejected. The panel says: Rejected. Returned to the organization for changes, and History shows your remarks. The Admin is told. | M44: Not run
A45: DH-044 | B45: Approvals | C45: Approve a budget | D45: Functional | E45: High | F45: Any | G45: Any time | I45: The SAO has activated a semester first (SAO: Setup and records > Academic years > Add semester, then Set as active). A fresh seed has no semester. Admin 900001 has proposed a budget (Finance > Budgets, Propose budget) for PSITS-CCS. Sign in as Department Head 940001 (College of Computer Studies, home of PSITS-CCS). The password is given to you separately. | J45: 1. Open Approvals. 2. Set Request type to Budget. 3. Select Review on the budget row. 4. Select Approve and confirm. 5. Select Open budget in the panel. | K45: The request becomes Approved and Open budget leads to Finance > Budgets with the budget open. On the default setup this is the last step, so the budget shows Approved. | L45: VERIFY: if the SAO second step is switched on, the budget says Waiting for SAO approval instead. | M45: Not run
A46: DH-045 | B46: Approvals | C46: Approve a financial report: it then goes to the SAO | D46: Functional | E46: High | F46: Any | G46: Any time | I46: Admin 900001 has generated and submitted a financial report (Finance > Financial reports). Sign in as Department Head 940001 (College of Computer Studies, home of PSITS-CCS). The password is given to you separately. | J46: 1. Open Approvals. 2. Set Request type to Financial Report. 3. Select Review on the report row. 4. Look at the panel: Download submitted report, Required signatories, Supporting documents. 5. Select Approve and confirm. 6. Read the sentence at the top of the panel. | K46: The panel offers Download submitted report and lists the signatories and documents. After Approve the report moves on to the SAO (first stage only: the head cannot give final approval). The panel shows the report as Approved by you and Open report leads to Finance > Financial reports. | L46: VERIFY: the exact sentence after approval for a report. | M46: Not run
A47: DH-046 | B47: Approvals | C47: Approve an election proposal | D47: Functional | E47: Medium | F47: Any | G47: Any time | I47: The SAO has activated a semester first (SAO: Setup and records > Academic years > Add semester, then Set as active). A fresh seed has no semester. Admin 900001 has proposed an election (it waits for the Department Head). Sign in as Department Head 940001 (College of Computer Studies, home of PSITS-CCS). The password is given to you separately. | J47: 1. Open Approvals. 2. Set Request type to Election. 3. Select Review on the election row. 4. Select Approve and confirm. 5. Select Open election. | K47: The request becomes Approved. Open election leads to Election results (the head cannot open the election workspace). The Admin can now build the ballot. | L47: VERIFY: Election results may say results are not available yet because voting has not started. | M47: Not run
A48: DH-047 | B48: Approvals | C48: Head cannot decide a request that waits for the SAO | D48: Access | E48: High | F48: Any | G48: Any time | I48: A request the head already approved that now waits for the SAO (for example a financial report or an event with SAO files). Sign in as Department Head 940001 (College of Computer Studies, home of PSITS-CCS). The password is given to you separately. | J48: 1. Open Approvals. 2. Select All History. 3. Find the request you approved earlier. 4. Select Details. 5. Look for Approve and Reject buttons. | K48: The button on the row says Details, not Review. The panel shows the waiting stage (Waiting for SAO approval) and has NO Approve or Reject. The head cannot approve the SAO step. A request the head sent cannot be decided by the head either. | M48: Not run
A49: DH-048 | B49: Approvals | C49: Search requests by requester name or school ID | D49: Functional | E49: Medium | F49: Any | G49: Any time | I49: A semester is active. Admin 900001 (PSITS-CCS) has proposed an event with dates inside the semester, so it waits for the Department Head. Sign in as Department Head 940001 (College of Computer Studies, home of PSITS-CCS). The password is given to you separately. | J49: 1. Open Approvals. 2. Type the first name of the Admin who sent the request in Search requests. 3. Wait a moment and read the list. 4. Type a word that matches nobody, for example zzzz. 5. Select Clear filters in the empty message. | K49: The matching request stays. After zzzz the list says: No requests match these filters, with Try a different type, date range or search. Clear filters brings the rows back. The search looks at requester name, school ID, remarks and type, NOT at the request title. | L49: VERIFY: typing a title word may show nothing. | M49: Not run
A50: DH-049 | B50: Approvals | C50: Filter by request type | D50: Functional | E50: Medium | F50: Any | G50: Any time | I50: A semester is active. Admin 900001 (PSITS-CCS) has proposed an event with dates inside the semester, so it waits for the Department Head. At least one pending event and one pending budget or report. | J50: 1. Open Approvals. 2. Open Request type. 3. Read the options. 4. Choose Event. 5. Choose Budget. 6. Choose All request types. | K50: Options: All request types, Event, Budget, Election, Announcement, Payment, Financial Report. Each choice shows only that type and the count line updates. If a type has no pending rows the message No requests match these filters shows. | M50: Not run
A51: DH-050 | B51: Approvals | C51: Organization filter lists only organizations of the head college | D51: Access | E51: High | F51: Any | G51: Any time | I51: Sign in as Department Head 940001 (College of Computer Studies, home of PSITS-CCS). The password is given to you separately. | J51: 1. Open Approvals. 2. Open the Organization filter. 3. Read every option. 4. Choose PSITS-CCS (or the full name of it). 5. Choose All organizations. | K51: The options are All organizations and only organizations of the College of Computer Studies (PSITS-CCS and any the head registered). JPIA-CBE, FES-CTE, NSC-CHS and EIG-COE do NOT appear. Choosing one organization narrows the rows and the count. | M51: Not run
A52: DH-051 | B52: Approvals | C52: Date filters, including a range that ends before it starts | D52: Validation | E52: Low | F52: Any | G52: Any time | I52: A semester is active. Admin 900001 (PSITS-CCS) has proposed an event with dates inside the semester, so it waits for the Department Head. Sign in as Department Head 940001 (College of Computer Studies, home of PSITS-CCS). The password is given to you separately. | J52: 1. Open Approvals. 2. Set Requested from to a date in the past and Requested to to today. 3. Read the list. 4. Set Requested to to a date earlier than Requested from. 5. Read the page. 6. Select Reset. | K52: A valid range shows the requests sent in that range. An end date before the start date does not show a list; the page shows an error message such as Failed to load approval requests. | L52: VERIFY: exact wording for a bad range. Reset clears every filter. | M52: Not run
A53: DH-052 | B53: Approvals | C53: All History shows decided requests and their remarks | D53: Functional | E53: Medium | F53: Any | G53: Any time | I53: Sign in as Department Head 940001 (College of Computer Studies, home of PSITS-CCS). The password is given to you separately. The head has approved or rejected at least one request. | J53: 1. Open Approvals. 2. Select All History. 3. Find a request you rejected. 4. Read the remarks line under it. 5. Select Pending (n) to go back. | K53: All History lists pending and decided requests with badges Approved or Rejected. A rejected row shows Remarks: and your reason. Pending (n) still shows the count of waiting requests. | M53: Not run
A54: DH-053 | B54: Approvals | C54: Empty states: Nothing to review and No approval history yet | D54: Usability | E54: Medium | F54: Any | G54: Any time | I54: Sign in as a head whose college has no pending requests and no decided requests. VERIFY: reachable on 940003, 940004 or 940005 on a fresh seed if their organizations sent nothing; otherwise decide every pending request first. | J54: 1. Open Approvals. 2. Read the message under Pending. 3. Select All History. 4. Read the message. | K54: Pending says: Nothing to review. Events, budgets, elections and financial reports from the organizations in your college appear here for your decision. The organization Admin sends them. All History with no decisions says: No approval history yet. Requests you approve or reject are listed here afterwards. Export CSV is greyed out. | M54: Not run
A55: DH-054 | B55: Approvals | C55: Export CSV downloads the filtered list | D55: Functional | E55: Low | F55: Laptop | G55: Any time | I55: Sign in as Department Head 940001 (College of Computer Studies, home of PSITS-CCS). The password is given to you separately. At least one request in the list. | J55: 1. Open Approvals. 2. Choose a filter, for example Request type Event. 3. Select Export CSV. 4. Open the downloaded file. | K55: A file named approval-register-YYYY-MM-DD.csv (today date) downloads. It has a header row (Request ID, Organization, Type, Title, Status, Requester ID, Requester and more) and only the rows in the filtered list. When the count line shows 0 matching requests the Export CSV button is greyed out. | M55: Not run
A56: DH-055 | B56: Approvals | C56: A request that does not exist opens a safe message | D56: Negative | E56: Medium | F56: Any | G56: Any time | I56: Sign in as Department Head 940001 (College of Computer Studies, home of PSITS-CCS). The password is given to you separately. | J56: 1. Open Approvals. 2. In the address bar add ?record=999999 at the end and press Enter. 3. Read the panel. 4. Select the close button. | K56: A panel opens with: This request is not available to you, and Only the Department Head or Admin it was sent to, and the organization that sent it, can open it. It may also have been removed. No technical error shows. | M56: Not run
A57: DH-056 | B57: Approvals | C57: A request of another college cannot be opened | D57: Access | E57: High | F57: Any | G57: Any time | I57: A semester is active. Admin 900001 (PSITS-CCS) has proposed an event with dates inside the semester, so it waits for the Department Head. Sign in as 940002 (Business). Have the id of a CCS request from 940001 (the panel shows Request #id). | J57: 1. As 940001 open a request in Approvals and note the number after Request #. 2. Sign out and sign in as 940002. 3. Open Approvals. 4. Add ?record= and that number to the address and press Enter. 5. Read the panel. | K57: The panel says: This request is not available to you. The CCS request is not in the 940002 list either. The head of another college cannot read or decide it. | M57: Not run
A58: DH-057 | B58: Approvals | C58: Two people decide the same request: the second one is refused | D58: Negative | E58: Low | F58: Laptop | G58: Any time | I58: A semester is active. Admin 900001 (PSITS-CCS) has proposed an event with dates inside the semester, so it waits for the Department Head. Sign in as Department Head 940001 (College of Computer Studies, home of PSITS-CCS). The password is given to you separately. Open the same account in two browser tabs. | J58: 1. In tab 1 open Approvals and Review the request. 2. In tab 2 open Approvals and Review the same request. 3. In tab 1 Approve it and confirm. 4. In tab 2 select Approve and confirm. | K58: The second try is refused and the request is not changed twice. An error message shows such as Failed to submit review. Please try again. After a refresh the request shows Approved. | L58: VERIFY: the exact wording (the server says: This request has already been reviewed.). | M58: Not run
A59: DH-058 | B59: Approvals | C59: Phone: review and approve on a small screen | D59: Usability | E59: Medium | F59: Phone | G59: Any time | I59: A semester is active. Admin 900001 (PSITS-CCS) has proposed an event with dates inside the semester, so it waits for the Department Head. Sign in as Department Head 940001 (College of Computer Studies, home of PSITS-CCS). The password is given to you separately. Use a phone. | J59: 1. Open Approvals on the phone. 2. Scroll the filter area. 3. Tap Review on a request. 4. Scroll the panel to the buttons. 5. Tap Approve and then Approve in the window. | K59: Filters stack in one column. The panel and the decision window scroll and the buttons Reject and Approve can be reached and tapped. After approving the message Request approved. shows. No sideways scrolling. | M59: Not run
A60: DH-059 | B60: Top bar > Notifications | C60: A notification about an event approval opens that approval | D60: Functional | E60: High | F60: Any | G60: Any time | I60: A semester is active. Admin 900001 (PSITS-CCS) has proposed an event with dates inside the semester, so it waits for the Department Head. Sign in as Department Head 940001 (College of Computer Studies, home of PSITS-CCS). The password is given to you separately. | J60: 1. Select the bell in the top bar. 2. Find the notice about the event you were asked to approve. 3. Select the notice. 4. Read the panel that opens. | K60: Approvals opens with the panel for that exact request (Request #id) and the Approve button is there. Two taps from the home page. | M60: Not run
A61: DH-060 | B61: Top bar > Notifications | C61: A notification about a financial report opens that report approval | D61: Functional | E61: Medium | F61: Any | G61: Any time | I61: Admin 900001 has submitted a financial report. Sign in as Department Head 940001 (College of Computer Studies, home of PSITS-CCS). The password is given to you separately. | J61: 1. Select the bell. 2. Select the notice that names the report. 3. Read the panel. | K61: Approvals opens with that report open and the button Download submitted report is visible. | M61: Not run
A62: DH-061 | B62: Top bar > Notifications | C62: A notification about an organization opens that organization | D62: Functional | E62: Medium | F62: Any | G62: Any time | I62: The SAO has activated a semester first (SAO: Setup and records > Academic years > Add semester, then Set as active). A fresh seed has no semester. The SAO has returned a registration of this college. | J62: 1. Select the bell. 2. Select the notice Organization registration returned. 3. Read the panel. | K62: Organizations opens with the side panel of that organization. It says Returned: edit and resubmit and has the button Edit and resubmit. | M62: Not run
A63: DH-062 | B63: Top bar > Notifications | C63: Mark all as read and the empty message | D63: Usability | E63: Low | F63: Any | G63: Any time | I63: Sign in as Department Head 940001 (College of Computer Studies, home of PSITS-CCS). The password is given to you separately. At least one unread notification. For the empty message, use an account with none. | J63: 1. Select the bell and read the number badge. 2. Select Mark all as read. 3. Look at the badge and the notices. 4. On an account with no notices, select the bell. | K63: The badge number disappears and the unread blue marks go. An account with no notices shows a bell icon and: No notifications yet. | M63: Not run
A64: DH-063 | B64: College view (read only) > Finance > Budgets | C64: Budgets is view only for the head | D64: Access | E64: High | F64: Any | G64: Any time | I64: Sign in as Department Head 940001 (College of Computer Studies, home of PSITS-CCS). The password is given to you separately. | J64: 1. Select Finance in the menu. It opens Budgets. 2. Read the grey note at the top. 3. Look at the top right of the page for action buttons. 4. Look for the Organization drop down. 5. Open one budget if the list has one. | K64: The note says: View only. You can review and export these records; the organization admin records and changes them. There is NO Propose budget, Edit, Delete or Generate advice button. The Organization drop down starts on All organizations. The budget opens for reading only. | M64: Not run
A65: DH-064 | B65: College view (read only) > Finance > Budgets | C65: Organization drop down narrows Finance to one organization of the college | D65: Functional | E65: Medium | F65: Any | G65: Any time | I65: Sign in as Department Head 940001 (College of Computer Studies, home of PSITS-CCS). The password is given to you separately. | J65: 1. Open Finance > Budgets. 2. Open the Organization drop down and read the options. 3. Choose PSITS-CCS. 4. Note the rows and the Ledger net balance. 5. Choose All organizations. | K65: The options are All organizations and only organizations of the head college. Choosing one organization shows only its budgets and its net balance. The note Ledger net balance updates. | M65: Not run
A66: DH-065 | B66: College view (read only) > Finance > Budgets | C66: No budgets: the empty message tells who can add them | D66: Usability | E66: Medium | F66: Any | G66: Any time | I66: A head whose college has no budgets. VERIFY: for example 940004 or 940005 on a fresh seed. | J66: 1. Sign in as that head. 2. Open Finance > Budgets. 3. Read the message. | K66: The page says: No budgets to show yet. Only the organization Admin proposes budgets. They appear here, with their approval stage, once the Admin proposes one. There is no button to add one. | M66: Not run
A67: DH-066 | B67: College view (read only) > Finance > Ledger | C67: Ledger shows income and expenses without edit buttons | D67: Access | E67: High | F67: Any | G67: Any time | I67: Sign in as Department Head 940001 (College of Computer Studies, home of PSITS-CCS). The password is given to you separately. | J67: 1. Open Finance > Ledger. 2. Read the four tiles: Income, Expenses, Net balance, Ledger entries. 3. Read the table columns. 4. Look for Record transaction, Edit transaction and Delete transaction. | K67: The tiles show money amounts. The columns include Date, Description, Source, Payer / Recorder, Category, Type, Amount. There is NO Record transaction, Edit transaction or Delete transaction button. | M67: Not run
A68: DH-067 | B68: College view (read only) > Finance > Ledger | C68: Ledger search and filters, and the empty results message | D68: Functional | E68: Medium | F68: Any | G68: Any time | I68: Sign in as Department Head 940001 (College of Computer Studies, home of PSITS-CCS). The password is given to you separately. | J68: 1. Open Finance > Ledger. 2. Type a word in Search transactions and press Enter. 3. Open Filter by transaction type and choose Income. 4. Select Apply. 5. Type a word that matches nothing and press Enter. 6. Select Clear filters. | K68: Search and the type filter narrow the rows and the tiles. A search with no match says: No matching transactions, with Try a different search or clear the filters. Clear filters brings the list back. Other filters: Filter by academic semester, Filter by event, Filter from date, Filter to date. | M68: Not run
A69: DH-068 | B69: College view (read only) > Finance > Ledger | C69: No transactions: the empty message | D69: Usability | E69: Low | F69: Any | G69: Any time | I69: A head whose college has no ledger entries. VERIFY: reachable on a fresh seed only for colleges without seeded transactions. | J69: 1. Sign in as that head. 2. Open Finance > Ledger. 3. Read the message. | K69: The page says: No transactions to show yet. Only the organization Admin records transactions. Verified collections, cash advances, paid charges and orders post here by themselves. No add button. | M69: Not run
A70: DH-069 | B70: College view (read only) > Finance > Financial reports | C70: Financial reports: review saved reports, no way to create one | D70: Access | E70: Medium | F70: Any | G70: Any time | I70: Admin 900001 has saved at least one financial report. Sign in as Department Head 940001 (College of Computer Studies, home of PSITS-CCS). The password is given to you separately. | J70: 1. Open Finance > Financial reports. 2. Look for a section that generates a report. 3. Read the list Financial reports and its stage text. 4. Use Search report history and Filter reports by status. 5. Select Export Excel on Full Transaction Log. | K70: There is NO report generator. The list shows each saved report with its approval stage (waiting for the Department Head, the SAO, approved or returned). The filters narrow the list. Export Excel downloads a file. The two cards Full Transaction Log and Category Breakdown offer Export Excel and Print / Save PDF. | M70: Not run
... A76: DH-075 | B76: College view (read only) > Calendar | C76: Calendar search, filters and empty messages | D76: Functional | E76: Medium | F76: Any | G76: Any time | I76: Sign in as Department Head 940001 (College of Computer Studies, home of PSITS-CCS). The password is given to you separately. | J76: 1. Open Calendar and make sure List is selected. 2. Type a word in Search events. 3. Change Status to Approved. 4. Change Sort by to Title. 5. Type a word that matches nothing. 6. Select Clear filters. | K76: Search, Event date, Status and Sort by narrow the list. No match says: No events match these filters, with Change the search, date or status, or clear the filters to see every event in this period. A college with no events says: No events from your college yet, with the button Open approvals. | M76: Not run
A77: DH-076 | B77: College view (read only) > Calendar | C77: Open an event for reading only | D77: Access | E77: Medium | F77: Any | G77: Any time | I77: Sign in as Department Head 940001 (College of Computer Studies, home of PSITS-CCS). The password is given to you separately. At least one event in the list. | J77: 1. Open Calendar. 2. Select View details (phone) or open the row menu and select View event (laptop). 3. Read the event details. 4. Look for Edit, Approve, Check in and Cancel buttons. 5. Select Close event details. | K77: The event details open for reading: progress stage, dates, venue, tasks and attendance numbers. There is NO Edit, Cancel, Delete or check-in control. Close event details shuts it. | L77: VERIFY: whether the head can also see SAO event files in this view. | M77: Not run
A78: DH-077 | B78: College view (read only) > Calendar | C78: Calendar shows only events of the head college | D78: Access | E78: High | F78: Any | G78: Any time | I78: Sign in as 940002 (Business). PSITS-CCS has seeded events. | J78: 1. Open Calendar. 2. Read the event titles and the Organizer column. 3. Look for events of PSITS-CCS. | K78: Only events of Business college organizations show (or the empty message). Events of PSITS-CCS are not shown. | M78: Not run
A79: DH-078 | B79: College view (read only) > Election results | C79: Election results are read only and the head cannot vote | D79: Functional | E79: Medium | F79: Any | G79: Any time | I79: Sign in as Department Head 940001 (College of Computer Studies, home of PSITS-CCS). The password is given to you separately. | J79: 1. Select Election results in the menu. 2. Read the page. 3. If more than one election is listed, choose another under Available results. 4. Look for a Vote or Cast vote button. | K79: You see the results of an election of your college: Official final results or Live vote totals, with Ballots, Selections, Positions and Candidates tiles. If none is available the page says: Election results are not available yet. There is no voting button. | L79: VERIFY: with no election at all, what the page shows. | M79: Not run
A80: DH-079 | B80: College view (read only) > Election results | C80: Voting and the election workspace are refused to the head | D80: Access | E80: High | F80: Any | G80: Any time | I80: Sign in as Department Head 940001 (College of Computer Studies, home of PSITS-CCS). The password is given to you separately. | J80: 1. Type /dashboard/elections/cast-vote in the address bar and press Enter. 2. Type /dashboard/elections and press Enter. 3. Type /dashboard/elections/manage-elections and press Enter. 4. Type /dashboard/elections/manage-candidates and press Enter. | K80: The first two addresses end on Election results. The last two send you back to the Department Head Dashboard. At no point do you see a ballot, Vote button or candidate editor. | M80: Not run
A81: DH-080 | B81: College view (read only) > Announcements | C81: Announcements feed: read, search and filter | D81: Functional | E81: Medium | F81: Any | G81: Any time | I81: Sign in as Department Head 940001 (College of Computer Studies, home of PSITS-CCS). The password is given to you separately. At least one published announcement of an organization of this college or of the SAO. | J81: 1. Select Announcements in the menu. 2. Type a word in Search announcements. 3. Open Announcement category and choose one category. 4. Choose All categories. 5. Type a word that matches nothing. 6. Select Clear filters. | K81: Announcements show as cards. Search and category narrow the list. No match says: No announcements match, with Try a different search or category. With none at all the page says: No announcements yet. Your officers post them here. There is no button to write an announcement. | M81: Not run
A82: DH-081 | B82: College view (read only) > Announcements | C82: Writing announcements is closed to the head | D82: Access | E82: Medium | F82: Any | G82: Any time | I82: Sign in as Department Head 940001 (College of Computer Studies, home of PSITS-CCS). The password is given to you separately. | J82: 1. Type /dashboard/announcements/manage-announcements in the address bar and press Enter. 2. Type /dashboard/announcements/create-announcement and press Enter. 3. Type /dashboard/approval-requests/new and press Enter. | K82: Each address sends you back to the Department Head Dashboard. The head cannot create or manage announcements and cannot send a new request. | M82: Not run
A83: DH-082 | B83: Access limits | C83: Store, shopping and orders are refused to the head | D83: Access | E83: High | F83: Any | G83: Any time | I83: Sign in as Department Head 940001 (College of Computer Studies, home of PSITS-CCS). The password is given to you separately. | J83: 1. Look at the top bar for a shopping cart. 2. Type /dashboard/merchandise/order-merchandise in the address bar and press Enter. 3. Type /dashboard/merchandise/my-orders and press Enter. 4. Type /dashboard/merchandise/manage-orders and press Enter. 5. Type /dashboard/merchandise/manage-inventory and press Enter. | K83: There is no cart in the top bar. Every address sends you back to the Department Head Dashboard. The head cannot buy or manage merchandise. | M83: Not run
A84: DH-083 | B84: Access limits | C84: Admin, officer and task pages are refused to the head | D84: Access | E84: High | F84: Any | G84: Any time | I84: Sign in as Department Head 940001 (College of Computer Studies, home of PSITS-CCS). The password is given to you separately. | J84: 1. Type /dashboard/admin and press Enter. 2. Type /dashboard/admin/users and press Enter. 3. Type /dashboard/admin/positions and press Enter. 4. Type /dashboard/events/manage-events and press Enter. 5. Type /dashboard/tasks/task-board and press Enter. | K84: Every address sends you back to the Department Head Dashboard. The head cannot manage people, assign roles, edit events or use the task board. | M84: Not run
A85: DH-084 | B85: Access limits | C85: SAO pages are refused: no creating colleges, no approving own SAO step | D85: Access | E85: High | F85: Any | G85: Any time | I85: Sign in as Department Head 940001 (College of Computer Studies, home of PSITS-CCS). The password is given to you separately. | J85: 1. Type /dashboard/super-admin and press Enter. 2. Type /dashboard/super-admin/colleges and press Enter. 3. Type /dashboard/super-admin/organizations and press Enter. 4. Type /dashboard/super-admin/admins and press Enter. 5. Type /dashboard/super-admin/academic-years and press Enter. | K85: Every address sends you back to the Department Head Dashboard. The head cannot add colleges or Department Heads, review registrations, create administrators or open a semester. Only the SAO can. | M85: Not run
A86: DH-085 | B86: Access limits | C86: Records pages (compliance, venues, grievances, clearances, audit log) are refused | D86: Access | E86: Medium | F86: Any | G86: Any time | I86: Sign in as Department Head 940001 (College of Computer Studies, home of PSITS-CCS). The password is given to you separately. | J86: 1. Type /dashboard/compliance and press Enter. 2. Type /dashboard/venues and press Enter. 3. Type /dashboard/grievances and press Enter. 4. Type /dashboard/clearances and press Enter. 5. Type /dashboard/audit-logs and press Enter. | K86: Every address sends you back to the Department Head Dashboard. | M86: Not run
A87: DH-086 | B87: Access limits | C87: Unknown address, old Approvals address and signed out visit | D87: Negative | E87: Medium | F87: Any | G87: Any time | I87: Sign in as Department Head 940001 (College of Computer Studies, home of PSITS-CCS). The password is given to you separately. | J87: 1. Type /dashboard/nothing-here and press Enter. 2. Type /dashboard/approvals and press Enter. 3. Sign out. 4. Type /dashboard/department-head/approvals in the address bar and press Enter. | K87: The unknown address sends you to the Dashboard while signed in. /dashboard/approvals sends you to /dashboard/department-head/approvals. After signing out, the Approvals address sends you to the Sign in page. No data shows. | M87: Not run
A88: DH-087 | B88: Profile | C88: Update the mobile number and save | D88: Functional | E88: Medium | F88: Any | G88: Any time | I88: Sign in as Department Head 940001 (College of Computer Studies, home of PSITS-CCS). The password is given to you separately. | J88: 1. Select Profile at the bottom of the menu. 2. Read the box Personal information. 3. Type a mobile number in Mobile number (optional). 4. Select Save profile. 5. Refresh the page. | K88: Save profile is greyed out until you change something. After saving a message says: Profile changes saved. The number is still there after a refresh. Discard changes undoes edits you have not saved. | M88: Not run
A89: DH-088 | B89: Profile | C89: Profile needs a first name, last name and email | D89: Validation | E89: Medium | F89: Any | G89: Any time | I89: Sign in as Department Head 940001 (College of Computer Studies, home of PSITS-CCS). The password is given to you separately. | J89: 1. Open Profile. 2. Clear First name. 3. Select Save profile. 4. Read the message. 5. Select Discard changes. | K89: Nothing is saved. The red message says: First name, last name, and email are required. Discard changes restores the old name. | M89: Not run
A90: DH-089 | B90: Profile | C90: Password change: empty, short and mismatching entries are refused | D90: Validation | E90: Medium | F90: Any | G90: Any time | I90: Sign in as Department Head 940001 (College of Computer Studies, home of PSITS-CCS). The password is given to you separately. Do not finish a real password change on a shared account unless the team agreed. | J90: 1. Open Profile and find Password & security. 2. Select the save button with all three boxes empty. 3. Fill the three boxes with a new password of only 5 characters and select save. 4. Fill a new password of 8 or more characters and a different Confirm new password and select save. 5. Read each message. | K90: Messages in order: Current password, new password, and confirmation are required. New password must be at least 8 characters. New passwords do not match. No password is changed. | M90: Not run
A91: DH-090 | B91: Study objectives | C91: Study objectives page opens for the head | D91: Functional | E91: Low | F91: Any | G91: Any time | I91: Sign in as Department Head 940001 (College of Computer Studies, home of PSITS-CCS). The password is given to you separately. | J91: 1. Select Study objectives at the bottom of the menu. 2. Read the page. 3. Select Dashboard. | K91: The page opens without an error and shows the study objectives with evidence for the head college. | L91: VERIFY: what the head sees on this page (it is scoped to the head college). | M91: Not run
A92: DH-091 | B92: Study objectives | C92: Study objectives evidence links open pages the head may see | D92: Access | E92: Low | F92: Any | G92: Any time | I92: Sign in as Department Head 940001. The password is given to you separately. Some activity exists in the college. | J92: 1. Scroll to the bottom of the left menu and select Study objectives. 2. Select a tile with an arrow, for example "Events completed" or "Transactions recorded in the ledger". 3. Go back and select "Expense forecasts generated (OLS regression)" or "Votes cast". 4. Go back and select a tile such as "Orders placed" or "Check-ins recorded manually". 5. Write down which tiles are links and the page each one opened. | K92: Linked tiles open pages of the college view: Calendar, Budgets, Ledger, Forecast, Election results. They never end in a redirect to the Dashboard. Tiles about orders, check-ins, tasks and announcements have no arrow, because the head has no page for them. | L92: VERIFY: the exact linked tiles (from the server route list: Forecast, Budgets, Ledger, Calendar, Elections and Election results). | M92: Not run
A93: DH-092 | B93: College view (read only) > Finance > Forecast | C93: A forecast that the Admin generated is shown read only to the head | D93: Access | E93: Medium | F93: Any | G93: Any time | H93: Run after ADM-147 | I93: Sign in as Department Head 940001. The password is given to you separately. Admin 900001 of PSITS-CCS has generated a forecast (ADM-147), so the page is not empty. | J93: 1. Open Finance > Forecast under College view. 2. Read the forecast card: its title, Income, Balance, Safe spend, Risk and the engine badge. 3. Look at the top of the page for "Generate forecast" and at the card for a delete button. 4. Use the Organization drop down to choose PSITS-CCS and then All organizations. | K93: The card "Forecast for <period>" shows the figures, the risk and the chart. There is no "Generate forecast" button and no delete button anywhere, only the Admin has them. The Organization drop down narrows the page to one organization of the college (VERIFY that it also narrows the forecast cards). The "No forecasts to show yet" message does not show while a forecast exists. | M93: Not run

Sheet Admin & Adviser
A1: ID | B1: Module | C1: Test case | D1: Type | E1: Priority | F1: Device | G1: Round | H1: Depends on | I1: Preconditions | J1: Steps | K1: Expected result | L1: Author note (unconfirmed) | M1: Status | N1: Severity | O1: Tester | P1: Date tested | Q1: Device and browser used | R1: Actual result / notes | S1: Bug screenshot link
A2: ADM-001 | B2: Sign in > Dashboard | C2: Admin signs in and lands on the Dashboard | D2: Functional | E2: High | F2: Any | G2: Any time | I2: A seeded copy is running and you have its address. You are signed out. Use Admin 900001 and the password from the tester sheet. | J2: 1. Open the HIUSA address you were given. 2. Type 900001 in the box 'School ID / ID Number'. 3. Type the password in the box 'Password'. 4. Select 'Sign in'. 5. Look at the page title and the left menu. | K2: You land on the Dashboard (the address ends in /dashboard/admin). The menu shows your role as Organization Admin. The page shows either a 'Getting started' card or the 'Administration workspace' tiles. | M2: Not run
A3: ADM-002 | B3: Sign in > Adviser | C3: Adviser account 990002 gets the same menu and pages as an Admin | D3: Access | E3: High | F3: Any | G3: Any time | I3: Adviser 990002 (PSITS-CCS). The SAO assigned this account. Its password is the adviser password on the tester sheet, not the demo password. | J3: 1. Sign in with School ID 990002. 2. Compare the left menu with the Admin menu in the case above. 3. Open Members > People. 4. Open Members > Officer positions and find the Adviser row. 5. Open Finance > Budgets. | K3: The menu is the same as the Admin menu (Dashboard, Approvals, Members, Finance, Events and tasks, Voting, Store, Updates, Records, My activity). People, Officer positions and Budgets open. If an Adviser position row exists it says 'SAO managed' and has no edit or delete menu. | L3: VERIFY: whether the seed holds an Adviser position row. | M3: Not run
A4: ADM-003 | B4: Menu | C4: Left menu has the right groups, pages and order for an Admin | D4: Usability | E4: High | F4: Laptop | G4: Any time | I4: Signed in as Admin 900001 (President of PSITS-CCS). Use the password from the tester sheet. | J4: 1. Read the left menu from top to bottom. 2. Open each group to see its pages. 3. Scroll to the bottom of the menu. | K4: In order: Dashboard; Approvals; Members (People, Officer positions, Programs and sections); Finance (Budgets, Ledger, Collections and advances, Student accounts, Financial reports, Forecast); Events and tasks (Events, Venue booking, Planning, Tasks, AI delegation, Check-in); Voting (Elections, Results); Store (Inventory, Orders, Claim desk); Updates (Announcements, Feed); Records (Compliance, Grievances, Clearance signing, Audit log); My activity (Vote, Shop, My orders, My receipts, Statement of account). Profile and Study objectives sit at the bottom. No SAO, Department Head or student-only pages are listed. | M4: Not run
A5: ADM-004 | B5: Menu | C5: Reach a page from the menu on a phone | D5: Usability | E5: High | F5: Phone | G5: Any time | I5: Signed in as Admin 900001 (President of PSITS-CCS). Use the password from the tester sheet. Use a phone, or a browser window narrower than 640 pixels. | J5: 1. Tap 'Open menu' at the top. 2. Tap the group 'Events and tasks'. 3. Tap 'Events'. 4. Scroll down and sideways on the Events page. | K5: The menu opens as a drawer, the group opens, and the Events page loads with the title Events. The page does not scroll sideways and every button can be tapped. | M5: Not run
A6: ADM-005 | B6: Dashboard | C6: Summary cards show counts and open the right page | D6: Functional | E6: Medium | F6: Any | G6: Round 1 (before the SAO opens a semester) | I6: Signed in as Admin 900001 (President of PSITS-CCS). Use the password from the tester sheet. Round 1 (before the SAO opens a semester) shows the seeded events, tasks and election; see docs/MEMBER_TESTING.md section 3. | J6: 1. On the Dashboard read the four cards: Pending Orders, Approval Requests, Pending Tasks, New Announcements. 2. Select 'Pending Orders'. 3. Go back and select 'Approval Requests'. 4. Go back and select 'Pending Tasks'. 5. Go back and select 'New Announcements'. | K6: Each card shows a number. Pending Orders opens Store > Orders. Approval Requests opens Approvals. Pending Tasks opens Events and tasks > Tasks. New Announcements opens Updates > Feed. | M6: Not run
A7: ADM-006 | B7: Dashboard | C7: A brand new organization sees the first-run message and the Getting started steps | D7: Usability | E7: Medium | F7: Any | G7: Any time | I7: Use Admin 990032 (adviser of NSC-CHS). The seed leaves this organization with only its adviser, so no orders, approvals, tasks, announcements or ledger entries exist. If the page does not show the first-run message, someone already added data: ask the demo owner for a reset. Password is the adviser password on the tester sheet. | J7: 1. Sign in as 990032. 2. Read the middle of the Dashboard. 3. Find the 'Getting started' card and read its steps. 4. Select the button 'Plan your first event'. | K7: The Dashboard says 'Nothing has happened here yet' and offers 'Plan your first event'. The Getting started card lists steps such as 'Set up your officer positions', 'Add your members', 'Set up programs and sections', 'Propose your first budget' and 'Plan your first event', each with a button. The button opens Events and tasks > Events. | M7: Not run
A8: ADM-007 | B8: Dashboard | C8: A Getting started step is ticked after the work is done | D8: Functional | E8: Medium | F8: Any | G8: Any time | I8: Use Admin 990032 (NSC-CHS adviser). Do this while the step 'Set up your officer positions' is still undone; if it is already ticked, ask the demo owner for a reset. See docs/MEMBER_TESTING.md section 4, Admin journey 5. | J8: 1. Open the Dashboard and note the progress bar on Getting started. 2. Select the step 'Set up your officer positions'. 3. Add one position (see the Officer positions cases) and save. 4. Return to the Dashboard. | K8: The step 'Set up your officer positions' no longer appears as undone and the progress bar has moved up by one step. | M8: Not run
A9: ADM-008 | B9: Dashboard | C9: Financial status chart changes with the period | D9: Functional | E9: Low | F9: Any | G9: Any time | I9: Signed in as Admin 900001 (President of PSITS-CCS). Use the password from the tester sheet. | J9: 1. On the Dashboard find the card 'Financial status'. 2. Change the 'Financial status period' to 3 months, then 6 months, then 12 months. 3. If no money was recorded, read the message under the chart. 4. Select 'Open ledger'. | K9: The chart redraws for each period. With no entries it says 'No ledger transactions in this period.' and offers 'Propose a budget'. 'Open ledger' opens Finance > Ledger. | M9: Not run
A10: ADM-009 | B10: Dashboard | C10: Latest announcements panel and its three buttons | D10: Functional | E10: Low | F10: Any | G10: Any time | I10: Signed in as Admin 900001 (President of PSITS-CCS). Use the password from the tester sheet. | J10: 1. On the Dashboard find the 'Announcements' panel with the heading 'Latest updates'. 2. Select 'New announcement'. 3. Go back and select 'Manage announcements'. 4. Go back and select 'View Feed'. | K10: The panel lists published announcements, or says 'No published announcements yet.' The three buttons open the new announcement form, the Announcements page and the Feed. | M10: Not run
A11: ADM-010 | B11: Access | C11: Admin cannot open SAO pages by typing the address | D11: Access | E11: High | F11: Any | G11: Any time | I11: Signed in as Admin 900001 (President of PSITS-CCS). Use the password from the tester sheet. | J11: 1. In the address bar type the address of your site followed by /dashboard/super-admin and press Enter. 2. Try /dashboard/super-admin/organizations. 3. Try /dashboard/super-admin/compliance. | K11: No SAO page or SAO data is shown. You are sent to a page you may use (normally your own Dashboard). | L11: VERIFY: the exact page you land on. | M11: Not run
A12: ADM-011 | B12: Access | C12: Admin cannot open Department Head, officer-only or student-only pages by typing the address | D12: Access | E12: High | F12: Any | G12: Any time | I12: Signed in as Admin 900001 (President of PSITS-CCS). Use the password from the tester sheet. | J12: 1. Type /dashboard/department-head/approvals after the site address and press Enter. 2. Type /dashboard/tasks/assigned-tasks (an officer page). 3. Type /dashboard/elections/manage-voters (an officer page). 4. Type /dashboard/my-grievances (a student page). 5. Open Voting > Elections, open an election and select the step 'Voters'. | K12: None of the typed pages opens for an Admin and you are sent to a page you may use. | L12: VERIFY: the exact page you land on. The 'Voters' step inside the election workspace does open a voter list with turnout. | M12: Not run
A13: ADM-012 | B13: Access | C13: Signed-out visitor is sent to the sign-in page | D13: Access | E13: High | F13: Any | G13: Any time | I13: Signed in as Admin 900001 (President of PSITS-CCS). Use the password from the tester sheet. | J13: 1. Select your name at the top right and sign out. 2. Type /dashboard/admin/users after the site address and press Enter. 3. Type /dashboard/finance/financial-ledger and press Enter. | K13: You see 'Sign in to HIUSA' each time. No Admin page content is shown. | M13: Not run
A14: ADM-013 | B14: Access | C14: A session that ended elsewhere sends you to sign in | D14: Negative | E14: Medium | F14: Laptop | G14: Any time | I14: Signed in as Admin 900001 (President of PSITS-CCS). Use the password from the tester sheet. | J14: 1. Open HIUSA in two browser tabs, both signed in as 900001. 2. In tab 2 sign out. 3. Go back to tab 1 and select Members > People. | K14: Tab 1 shows no data and takes you to the sign-in page instead of a broken page or a crash. | M14: Not run
A15: ADM-014 | B15: Members > People | C15: People page shows summary cards, the table and 10 users per page | D15: Functional | E15: High | F15: Laptop | G15: Any time | I15: Signed in as Admin 900001 (President of PSITS-CCS). Use the password from the tester sheet. | J15: 1. Open Members > People. 2. Read the cards: Total users, Students, Admins, Super admins. 3. Read the table headings. 4. Count the rows on the first page. | K15: Cards show counts. Table columns are School ID, Name, Role, Program / Major, Year Level, Section, Status, Actions. At most 10 rows show and a page control sits under the table. The Filtered user distribution chart is visible. | M15: Not run
A16: ADM-015 | B16: Members > People | C16: Search finds a user by name, school ID, program or email | D16: Functional | E16: High | F16: Any | G16: Any time | I16: Signed in as Admin 900001 (President of PSITS-CCS). Use the password from the tester sheet. | J16: 1. Open Members > People. 2. In 'Search name, school ID, program, or email' type 2100142. 3. Wait a moment and read the table. 4. Clear the box and type part of a last name. 5. Type zzzzzz in the search box. | K16: The list narrows to matching users and the result count updates (for example 1 user). Clearing the box shows everyone again. A search with no match shows 'No users found.' and 0 users, with no error. | M16: Not run
A17: ADM-016 | B17: Members > People | C17: Filter users by role and account status | D17: Functional | E17: Medium | F17: Any | G17: Any time | I17: Signed in as Admin 900001 (President of PSITS-CCS). Use the password from the tester sheet. | J17: 1. Open Members > People. 2. Choose 'Student' in the first dropdown (All roles). 3. Choose 'Active' in 'Filter by account status'. 4. Change the status to 'Disabled'. 5. Use the Clear option on the filter chips. | K17: Only matching users show each time. A chip for each active filter appears. Clear returns to all users and the first page. | M17: Not run
A18: ADM-017 | B18: Members > People | C18: Filter users by program, year level and section | D18: Functional | E18: Medium | F18: Laptop | G18: Any time | I18: Signed in as Admin 900001 (President of PSITS-CCS). Use the password from the tester sheet. At least one program with sections exists (the seed has BS Information Technology). | J18: 1. Open Members > People. 2. Choose a program in 'Filter by program'. 3. Choose '1st Year' in 'Filter by year level'. 4. Open 'Filter by section' and read the options. | K18: The list shows only students of that program and year. The section list shows only sections of that program and year. Changing the program resets the section. | M18: Not run
A19: ADM-018 | B19: Members > People | C19: Sort users and change pages | D19: Functional | E19: Low | F19: Any | G19: Any time | I19: Signed in as Admin 900001 (President of PSITS-CCS). Use the password from the tester sheet. More than 10 users exist (the seed has about 16 students). | J19: 1. Open Members > People. 2. Open 'Sort users' and choose 'School ID'. 3. Choose 'Newest accounts'. 4. Select the next page in the page control. 5. Type a name in the search box. | K19: The rows reorder for each choice. Page 2 shows the remaining users. After a search the list goes back to page 1. | M19: Not run
A20: ADM-019 | B20: Members > People | C20: Create a student account | D20: Functional | E20: High | F20: Any | G20: Any time | I20: Signed in as Admin 900001 (President of PSITS-CCS). Use the password from the tester sheet. A program exists. Use a school ID that does not exist yet, for example 2999001. | J20: 1. Open Members > People and select 'New User'. 2. Fill School ID, Email, First Name and Last Name. 3. Leave Role as Student and choose a Course / Program, Year Level and Section. 4. Type a Password and the same text in Confirm Password (at least 8 characters). 5. Select 'Create User'. | K20: The dialog closes with the message 'User account created.' The student appears in the table as Active with the program, year and section you chose. | M20: Not run
A21: ADM-020 | B21: Members > People | C21: Create user form: dependent dropdowns and the position field | D21: Usability | E21: Medium | F21: Laptop | G21: Any time | I21: Signed in as Admin 900001 (President of PSITS-CCS). Use the password from the tester sheet. | J21: 1. Select 'New User'. 2. Note the Year Level and Section boxes before choosing a program. 3. Choose a Course / Program, then a Year Level, then open Section. 4. Change Role to 'SBO Officer' and look for 'Organization Position'. 5. Change Role back to 'Student'. | K21: Year Level stays disabled until a program is chosen and Section stays disabled until a year is chosen. The Section list shows only sections of that program and year. 'Organization Position' appears for SBO Officer and Admin only and disappears for Student. | M21: Not run
A22: ADM-021 | B22: Members > People | C22: Create user: required fields and a student without a program | D22: Validation | E22: High | F22: Any | G22: Any time | I22: Signed in as Admin 900001 (President of PSITS-CCS). Use the password from the tester sheet. | J22: 1. Select 'New User'. 2. Leave everything empty and select 'Create User'. 3. Fill every required field but leave Course / Program empty for a Student. 4. Select 'Create User'. | K22: The browser asks for the empty required fields (marked with *). With no program the form says 'Choose a course/program for this student.' No account is created. | M22: Not run
A23: ADM-022 | B23: Members > People | C23: Create user: duplicate school ID or email is refused | D23: Validation | E23: High | F23: Any | G23: Any time | I23: Signed in as Admin 900001 (President of PSITS-CCS). Use the password from the tester sheet. | J23: 1. Select 'New User'. 2. Type School ID 2100142 (already used) with a new email and a valid password. 3. Select 'Create User'. 4. Change the School ID to a new number and use the email of another user in your organization. 5. Select 'Create User' again. | K23: Each attempt stays open and shows a red message under the field (for example that the school ID or email is already taken). | L23: VERIFY: exact wording. No second account is created. | M23: Not run
A24: ADM-023 | B24: Members > People | C24: Create user: password rules and bad values | D24: Validation | E24: Medium | F24: Any | G24: Any time | I24: Signed in as Admin 900001 (President of PSITS-CCS). Use the password from the tester sheet. | J24: 1. Select 'New User' and fill all required fields. 2. Type a Password of 5 characters and the same in Confirm Password, then select 'Create User'. 3. Type a valid Password and a different text in Confirm Password, then select 'Create User'. 4. Put letters in Contact Number and select 'Create User'. 5. Type 123456789 (nine digits) as School ID and select 'Create User'. | K24: Each attempt is refused with a message under the field: the password must be at least 8 characters, the confirmation must match, the contact number may only hold digits, + - ( ) and spaces, and the School ID may hold at most 8 digits. | L24: VERIFY: exact wording. | M24: Not run
A25: ADM-024 | B25: Members > People | C25: Create an SBO Officer with an organization position | D25: Functional | E25: Medium | F25: Any | G25: Any time | I25: Signed in as Admin 900001 (President of PSITS-CCS). Use the password from the tester sheet. At least one active SBO Officer position exists (see Officer positions). | J25: 1. Select 'New User'. 2. Set Role to 'SBO Officer'. 3. Open 'Organization Position' and choose a position. 4. Fill the other required fields and select 'Create User'. | K25: The account is created and shows Role SBO Officer. The View profile dialog shows the position under 'Organization position'. Only active positions are in the list, and 'Adviser' is never offered. | M25: Not run
A26: ADM-025 | B26: Members > People | C26: Admin cannot create a Department Head account | D26: Access | E26: High | F26: Any | G26: Any time | I26: Signed in as Admin 900001 (President of PSITS-CCS). Use the password from the tester sheet. | J26: 1. Select 'New User'. 2. Fill all required fields. 3. Set Role to 'Department Head'. 4. Select 'Create User'. | K26: The account is refused with a message that the role is not valid. Only the SAO creates Department Heads. No account is created. | M26: Not run
A27: ADM-026 | B27: Members > People | C27: Profile photo must be an image under 2 MB | D27: Validation | E27: Low | F27: Any | G27: Any time | I27: Signed in as Admin 900001 (President of PSITS-CCS). Use the password from the tester sheet. Have a PDF file and an image larger than 2 MB ready. | J27: 1. Select 'New User' and fill the required fields. 2. In 'Profile photo (optional)' choose the PDF file. 3. Select 'Create User'. 4. Choose the large image instead and select 'Create User' again. | K27: Each attempt shows 'Choose a JPEG, PNG, or WebP image up to 2 MB.' and nothing is created. A small JPEG or PNG is accepted. | M27: Not run
A28: ADM-027 | B28: Members > People | C28: Edit a student account | D28: Functional | E28: High | F28: Any | G28: Any time | I28: Signed in as Admin 900001 (President of PSITS-CCS). Use the password from the tester sheet. | J28: 1. Open Members > People and open the row menu (three dots) of a student. 2. Select 'Edit user'. 3. Try to type in the School ID box. 4. Change the Last Name and the Section. 5. Select 'Save Changes'. | K28: School ID is greyed out and cannot be changed. The dialog closes with 'User account updated.' and the table shows the new values. | M28: Not run
A29: ADM-028 | B29: Members > People | C29: Edit: an email used by someone else is refused | D29: Validation | E29: Medium | F29: Any | G29: Any time | I29: Signed in as Admin 900001 (President of PSITS-CCS). Use the password from the tester sheet. | J29: 1. Open the row menu of a student and select 'Edit user'. 2. Replace the email with the email of another student in your organization. 3. Select 'Save Changes'. | K29: The dialog stays open with a red message that the email is already taken. The old email is kept. | M29: Not run
A30: ADM-029 | B30: Members > People | C30: Admin accounts cannot be edited, deactivated or deleted by an Admin | D30: Access | E30: High | F30: Any | G30: Any time | I30: Signed in as Admin 900001 (President of PSITS-CCS). Use the password from the tester sheet. Another Admin exists in PSITS-CCS (900002 or 900003). | J30: 1. Open Members > People and choose 'Admin' in the role dropdown. 2. Open the row menu of 900002. 3. Read every item in the menu. 4. Search 990002 (the Adviser) and read the items in its row menu. | K30: The menus offer View profile and fingerprint items but no 'Edit user', 'Deactivate account' or 'Delete profile'. Only the SAO manages Admin and Adviser accounts. | M30: Not run
A31: ADM-030 | B31: Members > People | C31: An Admin cannot delete or deactivate their own account | D31: Negative | E31: High | F31: Any | G31: Any time | I31: Signed in as Admin 900001 (President of PSITS-CCS). Use the password from the tester sheet. | J31: 1. Open Members > People and search 900001. 2. Open the row menu of your own row. 3. Look for 'Delete profile' and 'Deactivate account'. | K31: Your own row offers no 'Delete profile' and no 'Deactivate account'. If the request is forced the system refuses with 'You cannot delete your own account.' | M31: Not run
A32: ADM-031 | B32: Members > People | C32: Deactivate a student (sign-in is refused), then reactivate | D32: Functional | E32: High | F32: Any | G32: Any time | I32: Signed in as Admin 900001 (President of PSITS-CCS). Use the password from the tester sheet. Use a test student you created, not a shared demo student. | J32: 1. Open the row menu of the test student and select 'Deactivate account', then 'Deactivate' in 'Deactivate User'. 2. Read the message and the Status column. 3. In a private window try to sign in as that student. 4. Back in People open the row menu and select 'Reactivate account', then 'Reactivate' in 'Reactivate User'. 5. Read the message and the Status column. | K32: After deactivating the message reads '<name> was deactivated.', Status shows Inactive and the student sees 'This account cannot sign in right now. Contact your organization admin for help.' After reactivating the message reads '<name> was reactivated.' and Status shows Active. The dialog warns the student may still need to reset a password. | M32: Not run
